<?xml version="1.0" encoding="UTF-8" standalone="yes"?>
<w:document xmlns:wpc="http://schemas.microsoft.com/office/word/2010/wordprocessingCanvas" xmlns:cx="http://schemas.microsoft.com/office/drawing/2014/chartex" xmlns:cx1="http://schemas.microsoft.com/office/drawing/2015/9/8/chartex" xmlns:cx2="http://schemas.microsoft.com/office/drawing/2015/10/21/chartex" xmlns:cx3="http://schemas.microsoft.com/office/drawing/2016/5/9/chartex" xmlns:cx4="http://schemas.microsoft.com/office/drawing/2016/5/10/chartex" xmlns:cx5="http://schemas.microsoft.com/office/drawing/2016/5/11/chartex" xmlns:cx6="http://schemas.microsoft.com/office/drawing/2016/5/12/chartex" xmlns:cx7="http://schemas.microsoft.com/office/drawing/2016/5/13/chartex" xmlns:cx8="http://schemas.microsoft.com/office/drawing/2016/5/14/chartex" xmlns:mc="http://schemas.openxmlformats.org/markup-compatibility/2006" xmlns:aink="http://schemas.microsoft.com/office/drawing/2016/ink" xmlns:am3d="http://schemas.microsoft.com/office/drawing/2017/model3d" xmlns:o="urn:schemas-microsoft-com:office:office" xmlns:r="http://schemas.openxmlformats.org/officeDocument/2006/relationships" xmlns:m="http://schemas.openxmlformats.org/officeDocument/2006/math" xmlns:v="urn:schemas-microsoft-com:vml" xmlns:wp14="http://schemas.microsoft.com/office/word/2010/wordprocessingDrawing" xmlns:wp="http://schemas.openxmlformats.org/drawingml/2006/wordprocessingDrawing" xmlns:w10="urn:schemas-microsoft-com:office:word" xmlns:w="http://schemas.openxmlformats.org/wordprocessingml/2006/main" xmlns:w14="http://schemas.microsoft.com/office/word/2010/wordml" xmlns:w15="http://schemas.microsoft.com/office/word/2012/wordml" xmlns:w16cex="http://schemas.microsoft.com/office/word/2018/wordml/cex" xmlns:w16cid="http://schemas.microsoft.com/office/word/2016/wordml/cid" xmlns:w16="http://schemas.microsoft.com/office/word/2018/wordml" xmlns:w16sdtdh="http://schemas.microsoft.com/office/word/2020/wordml/sdtdatahash" xmlns:w16se="http://schemas.microsoft.com/office/word/2015/wordml/symex" xmlns:wpg="http://schemas.microsoft.com/office/word/2010/wordprocessingGroup" xmlns:wpi="http://schemas.microsoft.com/office/word/2010/wordprocessingInk" xmlns:wne="http://schemas.microsoft.com/office/word/2006/wordml" xmlns:wps="http://schemas.microsoft.com/office/word/2010/wordprocessingShape" mc:Ignorable="w14 w15 w16se w16cid w16 w16cex w16sdtdh wp14"><w:body><w:tbl><w:tblPr><w:tblW w:w="9213" w:type="dxa"/><w:tblInd w:w="-34" w:type="dxa"/><w:tblLayout w:type="fixed"/><w:tblLook w:val="04A0" w:firstRow="1" w:lastRow="0" w:firstColumn="1" w:lastColumn="0" w:noHBand="0" w:noVBand="1"/></w:tblPr><w:tblGrid><w:gridCol w:w="2835"/><w:gridCol w:w="2268"/><w:gridCol w:w="2126"/><w:gridCol w:w="1984"/></w:tblGrid><w:tr w:rsidR="0065760A" w:rsidRPr="00781917" w14:paraId="00B10AE4" w14:textId="77777777" w:rsidTr="00B87C11"><w:trPr><w:trHeight w:val="215"/></w:trPr><w:tc><w:tcPr><w:tcW w:w="2835" w:type="dxa"/><w:vAlign w:val="center"/></w:tcPr><w:p w14:paraId="7AA10F2D" w14:textId="77777777" w:rsidR="0065760A" w:rsidRPr="00781917" w:rsidRDefault="0065760A" w:rsidP="00B87C11"><w:pPr><w:rPr><w:rFonts w:ascii="Tahoma" w:hAnsi="Tahoma" w:cs="Tahoma"/><w:color w:val="626262"/><w:sz w:val="16"/><w:szCs w:val="16"/></w:rPr></w:pPr></w:p></w:tc><w:tc><w:tcPr><w:tcW w:w="2268" w:type="dxa"/><w:shd w:val="clear" w:color="auto" w:fill="auto"/><w:vAlign w:val="center"/></w:tcPr><w:p w14:paraId="0FD027D0" w14:textId="77777777" w:rsidR="0065760A" w:rsidRPr="00781917" w:rsidRDefault="0065760A" w:rsidP="00B87C11"><w:pPr><w:rPr><w:rFonts w:ascii="Tahoma" w:hAnsi="Tahoma" w:cs="Tahoma"/><w:color w:val="626262"/><w:sz w:val="16"/><w:szCs w:val="16"/></w:rPr></w:pPr></w:p></w:tc><w:tc><w:tcPr><w:tcW w:w="2126" w:type="dxa"/><w:vAlign w:val="center"/></w:tcPr><w:p w14:paraId="3F9410C8" w14:textId="77777777" w:rsidR="0065760A" w:rsidRPr="00781917" w:rsidRDefault="0065760A" w:rsidP="00B87C11"><w:pPr><w:rPr><w:rFonts w:ascii="Tahoma" w:hAnsi="Tahoma" w:cs="Tahoma"/><w:color w:val="626262"/><w:sz w:val="16"/><w:szCs w:val="16"/></w:rPr></w:pPr></w:p></w:tc><w:tc><w:tcPr><w:tcW w:w="1984" w:type="dxa"/><w:vMerge w:val="restart"/><w:vAlign w:val="center"/></w:tcPr><w:p w14:paraId="2E54A7AB" w14:textId="77777777" w:rsidR="0065760A" w:rsidRPr="00781917" w:rsidRDefault="0065760A" w:rsidP="00B87C11"><w:pPr><w:jc w:val="center"/><w:rPr><w:rFonts w:ascii="Tahoma" w:hAnsi="Tahoma" w:cs="Tahoma"/><w:color w:val="626262"/><w:sz w:val="10"/><w:szCs w:val="10"/></w:rPr></w:pPr><w:r w:rsidRPr="00437041"><w:rPr><w:rFonts w:ascii="Tahoma" w:hAnsi="Tahoma" w:cs="Tahoma"/><w:noProof/></w:rPr><w:drawing><wp:inline distT="0" distB="0" distL="0" distR="0" wp14:anchorId="6C2AA835" wp14:editId="3B83E5AD"><wp:extent cx="1152525" cy="1085850"/><wp:effectExtent l="0" t="0" r="9525" b="0"/><wp:docPr id="4" name="Рисунок 4" descr="07_лого ЗФ контур верт чб"/><wp:cNvGraphicFramePr><a:graphicFrameLocks xmlns:a="http://schemas.openxmlformats.org/drawingml/2006/main" noChangeAspect="1"/></wp:cNvGraphicFramePr><a:graphic xmlns:a="http://schemas.openxmlformats.org/drawingml/2006/main"><a:graphicData uri="http://schemas.openxmlformats.org/drawingml/2006/picture"><pic:pic xmlns:pic="http://schemas.openxmlformats.org/drawingml/2006/picture"><pic:nvPicPr><pic:cNvPr id="0" name="Picture 1" descr="07_лого ЗФ контур верт чб"/><pic:cNvPicPr><a:picLocks noChangeAspect="1" noChangeArrowheads="1"/></pic:cNvPicPr></pic:nvPicPr><pic:blipFill><a:blip r:embed="rId8"><a:extLst><a:ext uri="{28A0092B-C50C-407E-A947-70E740481C1C}"><a14:useLocalDpi xmlns:a14="http://schemas.microsoft.com/office/drawing/2010/main" val="0"/></a:ext></a:extLst></a:blip><a:srcRect/><a:stretch><a:fillRect/></a:stretch></pic:blipFill><pic:spPr bwMode="auto"><a:xfrm><a:off x="0" y="0"/><a:ext cx="1152525" cy="1085850"/></a:xfrm><a:prstGeom prst="rect"><a:avLst/></a:prstGeom><a:noFill/><a:ln><a:noFill/></a:ln></pic:spPr></pic:pic></a:graphicData></a:graphic></wp:inline></w:drawing></w:r></w:p></w:tc></w:tr><w:tr w:rsidR="0065760A" w:rsidRPr="00781917" w14:paraId="61E95F8F" w14:textId="77777777" w:rsidTr="00B87C11"><w:trPr><w:trHeight w:val="215"/></w:trPr><w:tc><w:tcPr><w:tcW w:w="2835" w:type="dxa"/><w:vAlign w:val="center"/></w:tcPr><w:p w14:paraId="22FB700C" w14:textId="77777777" w:rsidR="0065760A" w:rsidRPr="00781917" w:rsidRDefault="0065760A" w:rsidP="00B87C11"><w:pPr><w:rPr><w:rFonts w:ascii="Tahoma" w:hAnsi="Tahoma" w:cs="Tahoma"/><w:color w:val="626262"/><w:sz w:val="16"/><w:szCs w:val="16"/></w:rPr></w:pPr></w:p></w:tc><w:tc><w:tcPr><w:tcW w:w="2268" w:type="dxa"/><w:shd w:val="clear" w:color="auto" w:fill="auto"/><w:vAlign w:val="center"/></w:tcPr><w:p w14:paraId="23063E13" w14:textId="77777777" w:rsidR="0065760A" w:rsidRPr="00781917" w:rsidRDefault="0065760A" w:rsidP="00B87C11"><w:pPr><w:rPr><w:rFonts w:ascii="Tahoma" w:hAnsi="Tahoma" w:cs="Tahoma"/><w:color w:val="626262"/><w:sz w:val="16"/><w:szCs w:val="16"/></w:rPr></w:pPr></w:p></w:tc><w:tc><w:tcPr><w:tcW w:w="2126" w:type="dxa"/><w:vAlign w:val="center"/></w:tcPr><w:p w14:paraId="41882958" w14:textId="77777777" w:rsidR="0065760A" w:rsidRPr="00781917" w:rsidRDefault="0065760A" w:rsidP="00B87C11"><w:pPr><w:rPr><w:rFonts w:ascii="Tahoma" w:hAnsi="Tahoma" w:cs="Tahoma"/><w:color w:val="626262"/><w:sz w:val="16"/><w:szCs w:val="16"/></w:rPr></w:pPr></w:p></w:tc><w:tc><w:tcPr><w:tcW w:w="1984" w:type="dxa"/><w:vMerge/><w:vAlign w:val="center"/></w:tcPr><w:p w14:paraId="1FA6ED46" w14:textId="77777777" w:rsidR="0065760A" w:rsidRPr="00781917" w:rsidRDefault="0065760A" w:rsidP="00B87C11"><w:pPr><w:jc w:val="center"/><w:rPr><w:rFonts w:ascii="Arial" w:hAnsi="Arial"/><w:sz w:val="22"/></w:rPr></w:pPr></w:p></w:tc></w:tr><w:tr w:rsidR="0065760A" w:rsidRPr="00781917" w14:paraId="33BD48C0" w14:textId="77777777" w:rsidTr="00B87C11"><w:trPr><w:trHeight w:val="215"/></w:trPr><w:tc><w:tcPr><w:tcW w:w="2835" w:type="dxa"/><w:vAlign w:val="center"/></w:tcPr><w:p w14:paraId="5103D594" w14:textId="77777777" w:rsidR="0065760A" w:rsidRPr="00781917" w:rsidRDefault="0065760A" w:rsidP="00B87C11"><w:pPr><w:rPr><w:rFonts w:ascii="Tahoma" w:hAnsi="Tahoma" w:cs="Tahoma"/><w:color w:val="626262"/><w:sz w:val="16"/><w:szCs w:val="16"/></w:rPr></w:pPr></w:p></w:tc><w:tc><w:tcPr><w:tcW w:w="2268" w:type="dxa"/><w:shd w:val="clear" w:color="auto" w:fill="auto"/><w:vAlign w:val="center"/></w:tcPr><w:p w14:paraId="1B25666F" w14:textId="77777777" w:rsidR="0065760A" w:rsidRPr="00781917" w:rsidRDefault="0065760A" w:rsidP="00B87C11"><w:pPr><w:rPr><w:rFonts w:ascii="Tahoma" w:hAnsi="Tahoma" w:cs="Tahoma"/><w:color w:val="626262"/><w:sz w:val="16"/><w:szCs w:val="16"/></w:rPr></w:pPr></w:p></w:tc><w:tc><w:tcPr><w:tcW w:w="2126" w:type="dxa"/><w:vAlign w:val="center"/></w:tcPr><w:p w14:paraId="04D777BC" w14:textId="77777777" w:rsidR="0065760A" w:rsidRPr="00781917" w:rsidRDefault="0065760A" w:rsidP="00B87C11"><w:pPr><w:rPr><w:rFonts w:ascii="Tahoma" w:hAnsi="Tahoma" w:cs="Tahoma"/><w:color w:val="626262"/><w:sz w:val="16"/><w:szCs w:val="16"/></w:rPr></w:pPr></w:p></w:tc><w:tc><w:tcPr><w:tcW w:w="1984" w:type="dxa"/><w:vMerge/></w:tcPr><w:p w14:paraId="59191EBE" w14:textId="77777777" w:rsidR="0065760A" w:rsidRPr="00781917" w:rsidRDefault="0065760A" w:rsidP="00B87C11"><w:pPr><w:rPr><w:rFonts w:ascii="Tahoma" w:hAnsi="Tahoma" w:cs="Tahoma"/><w:color w:val="626262"/><w:sz w:val="16"/><w:szCs w:val="16"/></w:rPr></w:pPr></w:p></w:tc></w:tr><w:tr w:rsidR="0065760A" w:rsidRPr="00781917" w14:paraId="5F77B7A8" w14:textId="77777777" w:rsidTr="00B87C11"><w:trPr><w:trHeight w:val="215"/></w:trPr><w:tc><w:tcPr><w:tcW w:w="2835" w:type="dxa"/><w:vAlign w:val="center"/></w:tcPr><w:p w14:paraId="7F9CAC89" w14:textId="77777777" w:rsidR="0065760A" w:rsidRPr="00781917" w:rsidRDefault="0065760A" w:rsidP="00B87C11"><w:pPr><w:rPr><w:rFonts w:ascii="Tahoma" w:hAnsi="Tahoma" w:cs="Tahoma"/><w:color w:val="626262"/><w:sz w:val="16"/><w:szCs w:val="16"/></w:rPr></w:pPr></w:p></w:tc><w:tc><w:tcPr><w:tcW w:w="2268" w:type="dxa"/><w:shd w:val="clear" w:color="auto" w:fill="auto"/><w:vAlign w:val="center"/></w:tcPr><w:p w14:paraId="38940C37" w14:textId="77777777" w:rsidR="0065760A" w:rsidRPr="00781917" w:rsidRDefault="0065760A" w:rsidP="00B87C11"><w:pPr><w:rPr><w:rFonts w:ascii="Tahoma" w:hAnsi="Tahoma" w:cs="Tahoma"/><w:color w:val="626262"/><w:sz w:val="16"/><w:szCs w:val="16"/></w:rPr></w:pPr></w:p></w:tc><w:tc><w:tcPr><w:tcW w:w="2126" w:type="dxa"/><w:vAlign w:val="center"/></w:tcPr><w:p w14:paraId="22A56AFB" w14:textId="77777777" w:rsidR="0065760A" w:rsidRPr="00781917" w:rsidRDefault="0065760A" w:rsidP="00B87C11"><w:pPr><w:rPr><w:rFonts w:ascii="Tahoma" w:hAnsi="Tahoma" w:cs="Tahoma"/><w:color w:val="626262"/><w:sz w:val="16"/><w:szCs w:val="16"/></w:rPr></w:pPr></w:p></w:tc><w:tc><w:tcPr><w:tcW w:w="1984" w:type="dxa"/><w:vMerge/></w:tcPr><w:p w14:paraId="3F05E039" w14:textId="77777777" w:rsidR="0065760A" w:rsidRPr="00781917" w:rsidRDefault="0065760A" w:rsidP="00B87C11"><w:pPr><w:rPr><w:rFonts w:ascii="Tahoma" w:hAnsi="Tahoma" w:cs="Tahoma"/><w:color w:val="626262"/><w:sz w:val="16"/><w:szCs w:val="16"/></w:rPr></w:pPr></w:p></w:tc></w:tr><w:tr w:rsidR="0065760A" w:rsidRPr="00781917" w14:paraId="3206D518" w14:textId="77777777" w:rsidTr="00B87C11"><w:trPr><w:trHeight w:val="215"/></w:trPr><w:tc><w:tcPr><w:tcW w:w="2835" w:type="dxa"/><w:vAlign w:val="center"/></w:tcPr><w:p w14:paraId="0ECD96C7" w14:textId="77777777" w:rsidR="0065760A" w:rsidRPr="00781917" w:rsidRDefault="0065760A" w:rsidP="00B87C11"><w:pPr><w:rPr><w:rFonts w:ascii="Tahoma" w:hAnsi="Tahoma" w:cs="Tahoma"/><w:color w:val="626262"/><w:sz w:val="16"/><w:szCs w:val="16"/></w:rPr></w:pPr></w:p></w:tc><w:tc><w:tcPr><w:tcW w:w="2268" w:type="dxa"/><w:shd w:val="clear" w:color="auto" w:fill="auto"/><w:vAlign w:val="center"/></w:tcPr><w:p w14:paraId="001E159B" w14:textId="77777777" w:rsidR="0065760A" w:rsidRPr="00781917" w:rsidRDefault="0065760A" w:rsidP="00B87C11"><w:pPr><w:rPr><w:rFonts w:ascii="Tahoma" w:hAnsi="Tahoma" w:cs="Tahoma"/><w:color w:val="626262"/><w:sz w:val="16"/><w:szCs w:val="16"/></w:rPr></w:pPr></w:p></w:tc><w:tc><w:tcPr><w:tcW w:w="2126" w:type="dxa"/><w:vAlign w:val="center"/></w:tcPr><w:p w14:paraId="1D2F8F76" w14:textId="77777777" w:rsidR="0065760A" w:rsidRPr="00781917" w:rsidRDefault="0065760A" w:rsidP="00B87C11"><w:pPr><w:rPr><w:rFonts w:ascii="Tahoma" w:hAnsi="Tahoma" w:cs="Tahoma"/><w:color w:val="626262"/><w:sz w:val="16"/><w:szCs w:val="16"/><w:lang w:val="en-US"/></w:rPr></w:pPr></w:p></w:tc><w:tc><w:tcPr><w:tcW w:w="1984" w:type="dxa"/><w:vMerge/></w:tcPr><w:p w14:paraId="449F6587" w14:textId="77777777" w:rsidR="0065760A" w:rsidRPr="00781917" w:rsidRDefault="0065760A" w:rsidP="00B87C11"><w:pPr><w:rPr><w:rFonts w:ascii="Tahoma" w:hAnsi="Tahoma" w:cs="Tahoma"/><w:color w:val="626262"/><w:sz w:val="16"/><w:szCs w:val="16"/><w:lang w:val="en-US"/></w:rPr></w:pPr></w:p></w:tc></w:tr><w:tr w:rsidR="0065760A" w:rsidRPr="00781917" w14:paraId="71A62D3C" w14:textId="77777777" w:rsidTr="00B87C11"><w:trPr><w:trHeight w:val="215"/></w:trPr><w:tc><w:tcPr><w:tcW w:w="2835" w:type="dxa"/><w:vAlign w:val="center"/></w:tcPr><w:p w14:paraId="4B29C685" w14:textId="77777777" w:rsidR="0065760A" w:rsidRPr="00781917" w:rsidRDefault="0065760A" w:rsidP="00B87C11"><w:pPr><w:rPr><w:rFonts w:ascii="Tahoma" w:hAnsi="Tahoma" w:cs="Tahoma"/><w:color w:val="626262"/><w:sz w:val="16"/><w:szCs w:val="16"/></w:rPr></w:pPr></w:p></w:tc><w:tc><w:tcPr><w:tcW w:w="2268" w:type="dxa"/><w:shd w:val="clear" w:color="auto" w:fill="auto"/><w:vAlign w:val="center"/></w:tcPr><w:p w14:paraId="1CB1BD20" w14:textId="77777777" w:rsidR="0065760A" w:rsidRPr="00781917" w:rsidRDefault="0065760A" w:rsidP="00B87C11"><w:pPr><w:rPr><w:rFonts w:ascii="Tahoma" w:hAnsi="Tahoma" w:cs="Tahoma"/><w:color w:val="626262"/><w:sz w:val="16"/><w:szCs w:val="16"/></w:rPr></w:pPr></w:p></w:tc><w:tc><w:tcPr><w:tcW w:w="2126" w:type="dxa"/><w:vAlign w:val="center"/></w:tcPr><w:p w14:paraId="69B1422C" w14:textId="77777777" w:rsidR="0065760A" w:rsidRPr="00781917" w:rsidRDefault="0065760A" w:rsidP="00B87C11"><w:pPr><w:rPr><w:rFonts w:ascii="Tahoma" w:hAnsi="Tahoma" w:cs="Tahoma"/><w:color w:val="626262"/><w:sz w:val="16"/><w:szCs w:val="16"/><w:lang w:val="en-US"/></w:rPr></w:pPr></w:p></w:tc><w:tc><w:tcPr><w:tcW w:w="1984" w:type="dxa"/><w:vMerge/></w:tcPr><w:p w14:paraId="5044921C" w14:textId="77777777" w:rsidR="0065760A" w:rsidRPr="00781917" w:rsidRDefault="0065760A" w:rsidP="00B87C11"><w:pPr><w:rPr><w:rFonts w:ascii="Tahoma" w:hAnsi="Tahoma" w:cs="Tahoma"/><w:color w:val="626262"/><w:sz w:val="16"/><w:szCs w:val="16"/><w:lang w:val="en-US"/></w:rPr></w:pPr></w:p></w:tc></w:tr><w:tr w:rsidR="0065760A" w:rsidRPr="00781917" w14:paraId="71278EC7" w14:textId="77777777" w:rsidTr="00B87C11"><w:trPr><w:trHeight w:val="215"/></w:trPr><w:tc><w:tcPr><w:tcW w:w="2835" w:type="dxa"/><w:vAlign w:val="center"/></w:tcPr><w:p w14:paraId="0F225AAD" w14:textId="77777777" w:rsidR="0065760A" w:rsidRPr="00781917" w:rsidRDefault="0065760A" w:rsidP="00B87C11"><w:pPr><w:rPr><w:rFonts w:ascii="Tahoma" w:hAnsi="Tahoma" w:cs="Tahoma"/><w:color w:val="626262"/><w:sz w:val="16"/><w:szCs w:val="16"/></w:rPr></w:pPr></w:p></w:tc><w:tc><w:tcPr><w:tcW w:w="2268" w:type="dxa"/><w:shd w:val="clear" w:color="auto" w:fill="auto"/><w:vAlign w:val="center"/></w:tcPr><w:p w14:paraId="33FD4656" w14:textId="77777777" w:rsidR="0065760A" w:rsidRPr="00781917" w:rsidRDefault="0065760A" w:rsidP="00B87C11"><w:pPr><w:rPr><w:rFonts w:ascii="Tahoma" w:hAnsi="Tahoma" w:cs="Tahoma"/><w:color w:val="626262"/><w:sz w:val="16"/><w:szCs w:val="16"/></w:rPr></w:pPr></w:p></w:tc><w:tc><w:tcPr><w:tcW w:w="2126" w:type="dxa"/><w:vAlign w:val="center"/></w:tcPr><w:p w14:paraId="16802085" w14:textId="77777777" w:rsidR="0065760A" w:rsidRPr="00781917" w:rsidRDefault="0065760A" w:rsidP="00B87C11"><w:pPr><w:rPr><w:rFonts w:ascii="Tahoma" w:hAnsi="Tahoma" w:cs="Tahoma"/><w:color w:val="626262"/><w:sz w:val="16"/><w:szCs w:val="16"/><w:lang w:val="en-US"/></w:rPr></w:pPr></w:p></w:tc><w:tc><w:tcPr><w:tcW w:w="1984" w:type="dxa"/><w:vMerge/></w:tcPr><w:p w14:paraId="4C6C4889" w14:textId="77777777" w:rsidR="0065760A" w:rsidRPr="00781917" w:rsidRDefault="0065760A" w:rsidP="00B87C11"><w:pPr><w:rPr><w:rFonts w:ascii="Tahoma" w:hAnsi="Tahoma" w:cs="Tahoma"/><w:color w:val="626262"/><w:sz w:val="16"/><w:szCs w:val="16"/><w:lang w:val="en-US"/></w:rPr></w:pPr></w:p></w:tc></w:tr><w:tr w:rsidR="0065760A" w:rsidRPr="00781917" w14:paraId="52E9432C" w14:textId="77777777" w:rsidTr="00B87C11"><w:trPr><w:trHeight w:val="215"/></w:trPr><w:tc><w:tcPr><w:tcW w:w="2835" w:type="dxa"/><w:vAlign w:val="center"/></w:tcPr><w:p w14:paraId="159D4E6C" w14:textId="77777777" w:rsidR="0065760A" w:rsidRPr="00781917" w:rsidRDefault="0065760A" w:rsidP="00B87C11"><w:pPr><w:rPr><w:rFonts w:ascii="Tahoma" w:hAnsi="Tahoma" w:cs="Tahoma"/><w:color w:val="626262"/><w:sz w:val="16"/><w:szCs w:val="16"/></w:rPr></w:pPr></w:p></w:tc><w:tc><w:tcPr><w:tcW w:w="2268" w:type="dxa"/><w:shd w:val="clear" w:color="auto" w:fill="auto"/><w:vAlign w:val="center"/></w:tcPr><w:p w14:paraId="4ED64EE3" w14:textId="77777777" w:rsidR="0065760A" w:rsidRPr="00781917" w:rsidRDefault="0065760A" w:rsidP="00B87C11"><w:pPr><w:rPr><w:rFonts w:ascii="Tahoma" w:hAnsi="Tahoma" w:cs="Tahoma"/><w:color w:val="626262"/><w:sz w:val="16"/><w:szCs w:val="16"/></w:rPr></w:pPr></w:p></w:tc><w:tc><w:tcPr><w:tcW w:w="2126" w:type="dxa"/><w:vAlign w:val="center"/></w:tcPr><w:p w14:paraId="0E9D4983" w14:textId="77777777" w:rsidR="0065760A" w:rsidRPr="00781917" w:rsidRDefault="0065760A" w:rsidP="00B87C11"><w:pPr><w:rPr><w:rFonts w:ascii="Tahoma" w:hAnsi="Tahoma" w:cs="Tahoma"/><w:color w:val="626262"/><w:sz w:val="16"/><w:szCs w:val="16"/><w:lang w:val="en-US"/></w:rPr></w:pPr></w:p></w:tc><w:tc><w:tcPr><w:tcW w:w="1984" w:type="dxa"/><w:vMerge/></w:tcPr><w:p w14:paraId="4319E169" w14:textId="77777777" w:rsidR="0065760A" w:rsidRPr="00781917" w:rsidRDefault="0065760A" w:rsidP="00B87C11"><w:pPr><w:rPr><w:rFonts w:ascii="Tahoma" w:hAnsi="Tahoma" w:cs="Tahoma"/><w:color w:val="626262"/><w:sz w:val="16"/><w:szCs w:val="16"/><w:lang w:val="en-US"/></w:rPr></w:pPr></w:p></w:tc></w:tr><w:tr w:rsidR="0065760A" w:rsidRPr="00781917" w14:paraId="2F4DB30B" w14:textId="77777777" w:rsidTr="00B87C11"><w:trPr><w:trHeight w:val="215"/></w:trPr><w:tc><w:tcPr><w:tcW w:w="2835" w:type="dxa"/><w:vAlign w:val="center"/></w:tcPr><w:p w14:paraId="59C2DA81" w14:textId="77777777" w:rsidR="0065760A" w:rsidRPr="00781917" w:rsidRDefault="0065760A" w:rsidP="00B87C11"><w:pPr><w:rPr><w:rFonts w:ascii="Tahoma" w:hAnsi="Tahoma" w:cs="Tahoma"/><w:color w:val="626262"/><w:sz w:val="16"/><w:szCs w:val="16"/></w:rPr></w:pPr></w:p></w:tc><w:tc><w:tcPr><w:tcW w:w="2268" w:type="dxa"/><w:shd w:val="clear" w:color="auto" w:fill="auto"/><w:vAlign w:val="center"/></w:tcPr><w:p w14:paraId="234579CE" w14:textId="77777777" w:rsidR="0065760A" w:rsidRPr="00781917" w:rsidRDefault="0065760A" w:rsidP="00B87C11"><w:pPr><w:rPr><w:rFonts w:ascii="Tahoma" w:hAnsi="Tahoma" w:cs="Tahoma"/><w:color w:val="626262"/><w:sz w:val="16"/><w:szCs w:val="16"/></w:rPr></w:pPr></w:p></w:tc><w:tc><w:tcPr><w:tcW w:w="2126" w:type="dxa"/><w:vAlign w:val="center"/></w:tcPr><w:p w14:paraId="3B5E9FBD" w14:textId="77777777" w:rsidR="0065760A" w:rsidRPr="00781917" w:rsidRDefault="0065760A" w:rsidP="00B87C11"><w:pPr><w:rPr><w:rFonts w:ascii="Tahoma" w:hAnsi="Tahoma" w:cs="Tahoma"/><w:color w:val="626262"/><w:sz w:val="16"/><w:szCs w:val="16"/><w:lang w:val="en-US"/></w:rPr></w:pPr></w:p></w:tc><w:tc><w:tcPr><w:tcW w:w="1984" w:type="dxa"/><w:vMerge/></w:tcPr><w:p w14:paraId="3822EF93" w14:textId="77777777" w:rsidR="0065760A" w:rsidRPr="00781917" w:rsidRDefault="0065760A" w:rsidP="00B87C11"><w:pPr><w:rPr><w:rFonts w:ascii="Tahoma" w:hAnsi="Tahoma" w:cs="Tahoma"/><w:color w:val="626262"/><w:sz w:val="16"/><w:szCs w:val="16"/><w:lang w:val="en-US"/></w:rPr></w:pPr></w:p></w:tc></w:tr></w:tbl><w:p w14:paraId="52DA8243" w14:textId="77777777" w:rsidR="0065760A" w:rsidRPr="00512446" w:rsidRDefault="0065760A" w:rsidP="00A423B1"><w:pPr><w:suppressAutoHyphens/><w:autoSpaceDE w:val="0"/><w:autoSpaceDN w:val="0"/><w:jc w:val="both"/><w:rPr><w:rFonts w:ascii="Tahoma" w:hAnsi="Tahoma" w:cs="Tahoma"/></w:rPr></w:pPr></w:p><w:p w14:paraId="23C4394E" w14:textId="77777777" w:rsidR="00B57A1B" w:rsidRPr="00512446" w:rsidRDefault="00B57A1B" w:rsidP="00A423B1"><w:pPr><w:suppressAutoHyphens/><w:autoSpaceDE w:val="0"/><w:autoSpaceDN w:val="0"/><w:jc w:val="both"/><w:rPr><w:rFonts w:ascii="Tahoma" w:hAnsi="Tahoma" w:cs="Tahoma"/></w:rPr></w:pPr></w:p><w:p w14:paraId="39D72D91" w14:textId="77777777" w:rsidR="00B57A1B" w:rsidRPr="00512446" w:rsidRDefault="00B57A1B" w:rsidP="00A423B1"><w:pPr><w:suppressAutoHyphens/><w:autoSpaceDE w:val="0"/><w:autoSpaceDN w:val="0"/><w:jc w:val="both"/><w:rPr><w:rFonts w:ascii="Tahoma" w:hAnsi="Tahoma" w:cs="Tahoma"/></w:rPr></w:pPr></w:p><w:tbl><w:tblPr><w:tblW w:w="9072" w:type="dxa"/><w:tblInd w:w="108" w:type="dxa"/><w:tblLook w:val="04A0" w:firstRow="1" w:lastRow="0" w:firstColumn="1" w:lastColumn="0" w:noHBand="0" w:noVBand="1"/></w:tblPr><w:tblGrid><w:gridCol w:w="5137"/><w:gridCol w:w="3935"/></w:tblGrid><w:tr w:rsidR="00EA3CBB" w:rsidRPr="003135AB" w14:paraId="7EB65C9A" w14:textId="77777777" w:rsidTr="00A423B1"><w:tc><w:tcPr><w:tcW w:w="5137" w:type="dxa"/><w:shd w:val="clear" w:color="auto" w:fill="auto"/></w:tcPr><w:p w14:paraId="0EFBF16A" w14:textId="77777777" w:rsidR="00EA3CBB" w:rsidRPr="003135AB" w:rsidRDefault="00EA3CBB" w:rsidP="00A423B1"><w:pPr><w:suppressAutoHyphens/><w:autoSpaceDE w:val="0"/><w:autoSpaceDN w:val="0"/><w:rPr><w:rFonts w:ascii="Tahoma" w:eastAsia="Calibri" w:hAnsi="Tahoma" w:cs="Tahoma"/></w:rPr></w:pPr></w:p></w:tc><w:tc><w:tcPr><w:tcW w:w="3935" w:type="dxa"/><w:shd w:val="clear" w:color="auto" w:fill="auto"/></w:tcPr><w:p w14:paraId="72692BE6" w14:textId="77777777" w:rsidR="00EA3CBB" w:rsidRPr="003135AB" w:rsidRDefault="00EA3CBB" w:rsidP="00A423B1"><w:pPr><w:ind w:right="-97"/><w:rPr><w:rFonts w:ascii="Tahoma" w:eastAsia="Calibri" w:hAnsi="Tahoma" w:cs="Tahoma"/></w:rPr></w:pPr><w:r w:rsidRPr="003135AB"><w:rPr><w:rFonts w:ascii="Tahoma" w:eastAsia="Calibri" w:hAnsi="Tahoma" w:cs="Tahoma"/></w:rPr><w:t>УТВЕРЖДАЮ</w:t></w:r></w:p><w:p w14:paraId="11F449CD" w14:textId="2DA02F95" w:rsidR="00EA3CBB" w:rsidRPr="00BC5181" w:rsidRDefault="005D2751" w:rsidP="00A423B1"><w:pPr><w:ind w:right="-142"/><w:rPr><w:rFonts w:ascii="Tahoma" w:eastAsia="Calibri" w:hAnsi="Tahoma" w:cs="Tahoma"/><w:lang w:eastAsia="en-US"/></w:rPr></w:pPr><w:r w:rsidR="00CD17DF" w:rsidRPr="00CD17DF"><w:rPr><w:rFonts w:ascii="Tahoma" w:hAnsi="Tahoma" w:cs="Tahoma"/></w:rPr><w:t>words</w:t></w:r></w:p><w:p w14:paraId="63BFF285" w14:textId="77777777" w:rsidR="00EA3CBB" w:rsidRPr="003135AB" w:rsidRDefault="00EA3CBB" w:rsidP="00A423B1"><w:pPr><w:ind w:right="-142"/><w:jc w:val="right"/><w:rPr><w:rFonts w:ascii="Tahoma" w:eastAsia="Calibri" w:hAnsi="Tahoma" w:cs="Tahoma"/></w:rPr></w:pPr></w:p><w:p w14:paraId="55C7C93B" w14:textId="560E5295" w:rsidR="00EA3CBB" w:rsidRPr="00BC5181" w:rsidRDefault="00BC5181" w:rsidP="00A423B1"><w:pPr><w:ind w:right="-97"/><w:jc w:val="right"/><w:rPr><w:rFonts w:ascii="Tahoma" w:eastAsia="Calibri" w:hAnsi="Tahoma" w:cs="Tahoma"/><w:lang w:val="en-US"/></w:rPr></w:pPr><w:proofErr w:type="gramStart"/><w:r w:rsidR="00CD17DF" w:rsidRPr="00CD17DF"><w:rPr><w:rFonts w:ascii="Tahoma" w:hAnsi="Tahoma" w:cs="Tahoma"/></w:rPr><w:t>words</w:t></w:r></w:p><w:p w14:paraId="6C7FD25E" w14:textId="77777777" w:rsidR="00EA3CBB" w:rsidRPr="003135AB" w:rsidRDefault="00924E3F" w:rsidP="00A423B1"><w:pPr><w:suppressAutoHyphens/><w:autoSpaceDE w:val="0"/><w:autoSpaceDN w:val="0"/><w:ind w:right="-142"/><w:jc w:val="both"/><w:rPr><w:rFonts w:ascii="Tahoma" w:eastAsia="Calibri" w:hAnsi="Tahoma" w:cs="Tahoma"/><w:iCs/></w:rPr></w:pPr><w:r><w:rPr><w:rFonts w:ascii="Tahoma" w:eastAsia="Calibri" w:hAnsi="Tahoma" w:cs="Tahoma"/></w:rPr><w:t>_____ ____________ 2022</w:t></w:r><w:r w:rsidR="00EA3CBB" w:rsidRPr="003135AB"><w:rPr><w:rFonts w:ascii="Tahoma" w:eastAsia="Calibri" w:hAnsi="Tahoma" w:cs="Tahoma"/></w:rPr><w:t xml:space="preserve"> г.</w:t></w:r></w:p></w:tc></w:tr></w:tbl><w:p w14:paraId="350B74E9" w14:textId="77777777" w:rsidR="004C4152" w:rsidRPr="00512446" w:rsidRDefault="004C4152" w:rsidP="004C4152"><w:pPr><w:suppressAutoHyphens/><w:autoSpaceDE w:val="0"/><w:autoSpaceDN w:val="0"/><w:ind w:left="5103" w:right="-2"/><w:rPr><w:rFonts w:ascii="Tahoma" w:hAnsi="Tahoma" w:cs="Tahoma"/></w:rPr></w:pPr></w:p><w:p w14:paraId="1390D6F4" w14:textId="77777777" w:rsidR="00D52A1D" w:rsidRPr="00512446" w:rsidRDefault="00D52A1D" w:rsidP="00A423B1"><w:pPr><w:suppressAutoHyphens/><w:autoSpaceDE w:val="0"/><w:autoSpaceDN w:val="0"/><w:jc w:val="center"/><w:rPr><w:rFonts w:ascii="Tahoma" w:hAnsi="Tahoma" w:cs="Tahoma"/><w:b/><w:bCs/></w:rPr></w:pPr><w:r w:rsidRPr="00512446"><w:rPr><w:rFonts w:ascii="Tahoma" w:hAnsi="Tahoma" w:cs="Tahoma"/><w:b/><w:bCs/></w:rPr><w:t>АКТ</w:t></w:r></w:p><w:p w14:paraId="36930CFB" w14:textId="77777777" w:rsidR="00883B74" w:rsidRPr="00512446" w:rsidRDefault="00883B74" w:rsidP="00D52A1D"><w:pPr><w:suppressAutoHyphens/><w:autoSpaceDE w:val="0"/><w:autoSpaceDN w:val="0"/><w:ind w:right="-2"/><w:jc w:val="center"/><w:rPr><w:rFonts w:ascii="Tahoma" w:hAnsi="Tahoma" w:cs="Tahoma"/><w:b/><w:bCs/></w:rPr></w:pPr></w:p><w:p w14:paraId="4265D7D1" w14:textId="77777777" w:rsidR="00D52A1D" w:rsidRPr="00512446" w:rsidRDefault="00DD2356" w:rsidP="00D52A1D"><w:pPr><w:widowControl w:val="0"/><w:suppressAutoHyphens/><w:autoSpaceDE w:val="0"/><w:autoSpaceDN w:val="0"/><w:ind w:right="-2"/><w:rPr><w:rFonts w:ascii="Tahoma" w:hAnsi="Tahoma" w:cs="Tahoma"/><w:sz w:val="20"/><w:szCs w:val="20"/></w:rPr></w:pPr><w:r><w:rPr><w:rFonts w:ascii="Tahoma" w:hAnsi="Tahoma" w:cs="Tahoma"/><w:sz w:val="20"/><w:szCs w:val="20"/></w:rPr><w:t>_</w:t></w:r><w:proofErr w:type="gramStart"/><w:r><w:rPr><w:rFonts w:ascii="Tahoma" w:hAnsi="Tahoma" w:cs="Tahoma"/><w:sz w:val="20"/><w:szCs w:val="20"/></w:rPr><w:t>_</w:t></w:r><w:r w:rsidR="00B7173F" w:rsidRPr="00512446"><w:rPr><w:rFonts w:ascii="Tahoma" w:hAnsi="Tahoma" w:cs="Tahoma"/><w:sz w:val="20"/><w:szCs w:val="20"/></w:rPr><w:t>.</w:t></w:r><w:r><w:rPr><w:rFonts w:ascii="Tahoma" w:hAnsi="Tahoma" w:cs="Tahoma"/><w:sz w:val="20"/><w:szCs w:val="20"/></w:rPr><w:t>_</w:t></w:r><w:proofErr w:type="gramEnd"/><w:r><w:rPr><w:rFonts w:ascii="Tahoma" w:hAnsi="Tahoma" w:cs="Tahoma"/><w:sz w:val="20"/><w:szCs w:val="20"/></w:rPr><w:t>_</w:t></w:r><w:r w:rsidR="0097077E" w:rsidRPr="00512446"><w:rPr><w:rFonts w:ascii="Tahoma" w:hAnsi="Tahoma" w:cs="Tahoma"/><w:sz w:val="20"/><w:szCs w:val="20"/></w:rPr><w:t>.</w:t></w:r><w:r w:rsidR="00D52A1D" w:rsidRPr="00512446"><w:rPr><w:rFonts w:ascii="Tahoma" w:hAnsi="Tahoma" w:cs="Tahoma"/><w:sz w:val="20"/><w:szCs w:val="20"/></w:rPr><w:t>20</w:t></w:r><w:r w:rsidR="00924E3F"><w:rPr><w:rFonts w:ascii="Tahoma" w:hAnsi="Tahoma" w:cs="Tahoma"/><w:sz w:val="20"/><w:szCs w:val="20"/></w:rPr><w:t>22</w:t></w:r><w:r w:rsidR="00BD2AFE" w:rsidRPr="00512446"><w:rPr><w:rFonts w:ascii="Tahoma" w:hAnsi="Tahoma" w:cs="Tahoma"/><w:sz w:val="20"/><w:szCs w:val="20"/></w:rPr><w:tab/></w:r><w:r w:rsidR="00BD2AFE" w:rsidRPr="00512446"><w:rPr><w:rFonts w:ascii="Tahoma" w:hAnsi="Tahoma" w:cs="Tahoma"/><w:sz w:val="20"/><w:szCs w:val="20"/></w:rPr><w:tab/></w:r><w:r w:rsidR="00BD2AFE" w:rsidRPr="00512446"><w:rPr><w:rFonts w:ascii="Tahoma" w:hAnsi="Tahoma" w:cs="Tahoma"/><w:sz w:val="20"/><w:szCs w:val="20"/></w:rPr><w:tab/></w:r><w:r w:rsidR="00BD2AFE" w:rsidRPr="00512446"><w:rPr><w:rFonts w:ascii="Tahoma" w:hAnsi="Tahoma" w:cs="Tahoma"/><w:sz w:val="20"/><w:szCs w:val="20"/></w:rPr><w:tab/></w:r><w:r w:rsidR="00BD2AFE" w:rsidRPr="00512446"><w:rPr><w:rFonts w:ascii="Tahoma" w:hAnsi="Tahoma" w:cs="Tahoma"/><w:sz w:val="20"/><w:szCs w:val="20"/></w:rPr><w:tab/></w:r><w:r w:rsidR="008F1DA7"><w:rPr><w:rFonts w:ascii="Tahoma" w:hAnsi="Tahoma" w:cs="Tahoma"/><w:sz w:val="20"/><w:szCs w:val="20"/></w:rPr><w:tab/></w:r><w:r w:rsidR="004C4152" w:rsidRPr="00512446"><w:rPr><w:rFonts w:ascii="Tahoma" w:hAnsi="Tahoma" w:cs="Tahoma"/><w:sz w:val="20"/><w:szCs w:val="20"/></w:rPr><w:tab/><w:t xml:space="preserve"> </w:t></w:r><w:r w:rsidR="00BD2AFE" w:rsidRPr="00512446"><w:rPr><w:rFonts w:ascii="Tahoma" w:hAnsi="Tahoma" w:cs="Tahoma"/><w:sz w:val="20"/><w:szCs w:val="20"/></w:rPr><w:t xml:space="preserve">       </w:t></w:r><w:r w:rsidR="00FE0ED3" w:rsidRPr="00512446"><w:rPr><w:rFonts w:ascii="Tahoma" w:hAnsi="Tahoma" w:cs="Tahoma"/><w:sz w:val="20"/><w:szCs w:val="20"/></w:rPr><w:t xml:space="preserve"> </w:t></w:r><w:r w:rsidR="008F1DA7"><w:rPr><w:rFonts w:ascii="Tahoma" w:hAnsi="Tahoma" w:cs="Tahoma"/><w:sz w:val="20"/><w:szCs w:val="20"/></w:rPr><w:tab/><w:t xml:space="preserve">     </w:t></w:r><w:r w:rsidR="00B42BE6"><w:rPr><w:rFonts w:ascii="Tahoma" w:hAnsi="Tahoma" w:cs="Tahoma"/><w:sz w:val="20"/><w:szCs w:val="20"/></w:rPr><w:t xml:space="preserve">    </w:t></w:r><w:r w:rsidR="008F1DA7"><w:rPr><w:rFonts w:ascii="Tahoma" w:hAnsi="Tahoma" w:cs="Tahoma"/><w:sz w:val="20"/><w:szCs w:val="20"/></w:rPr><w:t xml:space="preserve">  </w:t></w:r><w:r w:rsidR="0065760A"><w:rPr><w:rFonts w:ascii="Tahoma" w:hAnsi="Tahoma" w:cs="Tahoma"/><w:sz w:val="20"/><w:szCs w:val="20"/></w:rPr><w:tab/><w:t xml:space="preserve">      </w:t></w:r><w:r><w:rPr><w:rFonts w:ascii="Tahoma" w:hAnsi="Tahoma" w:cs="Tahoma"/><w:sz w:val="20"/><w:szCs w:val="20"/></w:rPr><w:t>№ ЗФ-89/___</w:t></w:r><w:r w:rsidR="00FE0ED3" w:rsidRPr="00512446"><w:rPr><w:rFonts w:ascii="Tahoma" w:hAnsi="Tahoma" w:cs="Tahoma"/><w:sz w:val="20"/><w:szCs w:val="20"/></w:rPr><w:t>-акт</w:t></w:r></w:p><w:p w14:paraId="58155693" w14:textId="77777777" w:rsidR="00D755B4" w:rsidRPr="00512446" w:rsidRDefault="00D755B4" w:rsidP="00D52A1D"><w:pPr><w:widowControl w:val="0"/><w:tabs><w:tab w:val="num" w:pos="284"/></w:tabs><w:suppressAutoHyphens/><w:autoSpaceDE w:val="0"/><w:autoSpaceDN w:val="0"/><w:ind w:right="-2"/><w:jc w:val="both"/><w:rPr><w:rFonts w:ascii="Tahoma" w:hAnsi="Tahoma" w:cs="Tahoma"/><w:color w:val="000000"/></w:rPr></w:pPr></w:p><w:p w14:paraId="45A72396" w14:textId="77777777" w:rsidR="000F3850" w:rsidRDefault="00986F08" w:rsidP="00E54D03"><w:pPr><w:widowControl w:val="0"/><w:tabs><w:tab w:val="num" w:pos="284"/></w:tabs><w:suppressAutoHyphens/><w:autoSpaceDE w:val="0"/><w:autoSpaceDN w:val="0"/><w:ind w:right="5103"/><w:rPr><w:rFonts w:ascii="Tahoma" w:hAnsi="Tahoma" w:cs="Tahoma"/><w:b/><w:color w:val="000000"/></w:rPr></w:pPr><w:r w:rsidRPr="00512446"><w:rPr><w:rFonts w:ascii="Tahoma" w:hAnsi="Tahoma" w:cs="Tahoma"/><w:b/><w:color w:val="000000"/></w:rPr><w:t xml:space="preserve">О проведении </w:t></w:r><w:r w:rsidR="00FF406A"><w:rPr><w:rFonts w:ascii="Tahoma" w:hAnsi="Tahoma" w:cs="Tahoma"/><w:b/><w:color w:val="000000"/></w:rPr><w:t>замеров</w:t></w:r></w:p><w:p w14:paraId="380D17B2" w14:textId="77777777" w:rsidR="00FF406A" w:rsidRDefault="00FF406A" w:rsidP="00E54D03"><w:pPr><w:widowControl w:val="0"/><w:tabs><w:tab w:val="num" w:pos="284"/></w:tabs><w:suppressAutoHyphens/><w:autoSpaceDE w:val="0"/><w:autoSpaceDN w:val="0"/><w:ind w:right="5103"/><w:rPr><w:rFonts w:ascii="Tahoma" w:hAnsi="Tahoma" w:cs="Tahoma"/><w:b/><w:color w:val="000000"/></w:rPr></w:pPr><w:r><w:rPr><w:rFonts w:ascii="Tahoma" w:hAnsi="Tahoma" w:cs="Tahoma"/><w:b/><w:color w:val="000000"/></w:rPr><w:t>категории удароопасности</w:t></w:r></w:p><w:p w14:paraId="6952D836" w14:textId="7D068F27" w:rsidR="00D52A1D" w:rsidRPr="00BA4665" w:rsidRDefault="00BA4665" w:rsidP="00E54D03"><w:pPr><w:widowControl w:val="0"/><w:tabs><w:tab w:val="num" w:pos="284"/></w:tabs><w:suppressAutoHyphens/><w:autoSpaceDE w:val="0"/><w:autoSpaceDN w:val="0"/><w:ind w:right="5103"/><w:rPr><w:rFonts w:ascii="Tahoma" w:hAnsi="Tahoma" w:cs="Tahoma"/><w:b/><w:color w:val="000000"/><w:lang w:val="en-US"/></w:rPr></w:pPr><w:r w:rsidR="00CD17DF" w:rsidRPr="00CD17DF"><w:rPr><w:rFonts w:ascii="Tahoma" w:hAnsi="Tahoma" w:cs="Tahoma"/></w:rPr><w:t>words</w:t></w:r><w:r w:rsidR="000F3850" w:rsidRPr="000F3850"><w:rPr><w:rFonts w:ascii="Tahoma" w:hAnsi="Tahoma" w:cs="Tahoma"/><w:b/><w:color w:val="000000"/></w:rPr><w:t xml:space="preserve">от </w:t></w:r><w:r w:rsidR="00CD17DF" w:rsidRPr="00CD17DF"><w:rPr><w:rFonts w:ascii="Tahoma" w:hAnsi="Tahoma" w:cs="Tahoma"/></w:rPr><w:t>words</w:t></w:r></w:p><w:p w14:paraId="2A3D7393" w14:textId="77777777" w:rsidR="00130D0B" w:rsidRPr="00512446" w:rsidRDefault="00130D0B" w:rsidP="00D52A1D"><w:pPr><w:widowControl w:val="0"/><w:tabs><w:tab w:val="num" w:pos="284"/></w:tabs><w:suppressAutoHyphens/><w:autoSpaceDE w:val="0"/><w:autoSpaceDN w:val="0"/><w:ind w:right="-2"/><w:jc w:val="both"/><w:rPr><w:rFonts w:ascii="Tahoma" w:hAnsi="Tahoma" w:cs="Tahoma"/><w:color w:val="000000"/></w:rPr></w:pPr></w:p><w:p w14:paraId="12878DB8" w14:textId="77777777" w:rsidR="00D52A1D" w:rsidRPr="00512446" w:rsidRDefault="001659AF" w:rsidP="002A554D"><w:pPr><w:widowControl w:val="0"/><w:suppressAutoHyphens/><w:autoSpaceDE w:val="0"/><w:autoSpaceDN w:val="0"/><w:ind w:firstLine="709"/><w:jc w:val="both"/><w:rPr><w:rFonts w:ascii="Tahoma" w:hAnsi="Tahoma" w:cs="Tahoma"/><w:color w:val="000000"/></w:rPr></w:pPr><w:r w:rsidRPr="00512446"><w:rPr><w:rFonts w:ascii="Tahoma" w:hAnsi="Tahoma" w:cs="Tahoma"/><w:color w:val="000000"/></w:rPr><w:t xml:space="preserve">Основание: </w:t></w:r><w:r w:rsidR="002720E7"><w:rPr><w:rFonts w:ascii="Tahoma" w:hAnsi="Tahoma" w:cs="Tahoma"/><w:color w:val="000000"/></w:rPr><w:t>приложение</w:t></w:r><w:r w:rsidR="002E44E6"><w:rPr><w:rFonts w:ascii="Tahoma" w:hAnsi="Tahoma" w:cs="Tahoma"/><w:color w:val="000000"/></w:rPr><w:t xml:space="preserve"> №</w:t></w:r><w:r w:rsidR="002720E7"><w:rPr><w:rFonts w:ascii="Tahoma" w:hAnsi="Tahoma" w:cs="Tahoma"/><w:color w:val="000000"/></w:rPr><w:t xml:space="preserve"> 8</w:t></w:r><w:r w:rsidR="002720E7" w:rsidRPr="002720E7"><w:rPr><w:rFonts w:ascii="Tahoma" w:hAnsi="Tahoma" w:cs="Tahoma"/><w:color w:val="000000"/></w:rPr><w:t xml:space="preserve"> «Указаний по безопасному ведению горных работ на Талнахском и Октябрьском месторождениях, склонных и опасных по горным ударам»</w:t></w:r></w:p><w:p w14:paraId="755491F9" w14:textId="77777777" w:rsidR="00D52A1D" w:rsidRPr="00512446" w:rsidRDefault="00D52A1D" w:rsidP="00D52A1D"><w:pPr><w:widowControl w:val="0"/><w:suppressAutoHyphens/><w:autoSpaceDE w:val="0"/><w:autoSpaceDN w:val="0"/><w:ind w:firstLine="709"/><w:jc w:val="both"/><w:rPr><w:rFonts w:ascii="Tahoma" w:hAnsi="Tahoma" w:cs="Tahoma"/><w:b/><w:color w:val="000000"/></w:rPr></w:pPr></w:p><w:tbl><w:tblPr><w:tblW w:w="0" w:type="auto"/><w:tblInd w:w="108" w:type="dxa"/><w:tblCellMar><w:left w:w="57" w:type="dxa"/><w:right w:w="57" w:type="dxa"/></w:tblCellMar><w:tblLook w:val="04A0" w:firstRow="1" w:lastRow="0" w:firstColumn="1" w:lastColumn="0" w:noHBand="0" w:noVBand="1"/></w:tblPr><w:tblGrid><w:gridCol w:w="2785"/><w:gridCol w:w="6178"/></w:tblGrid><w:tr w:rsidR="00666153" w:rsidRPr="00512446" w14:paraId="31D70D1C" w14:textId="77777777" w:rsidTr="000C7A08"><w:trPr><w:trHeight w:val="333"/></w:trPr><w:tc><w:tcPr><w:tcW w:w="9588" w:type="dxa"/><w:gridSpan w:val="2"/><w:shd w:val="clear" w:color="auto" w:fill="auto"/></w:tcPr><w:p w14:paraId="4870FE42" w14:textId="77777777" w:rsidR="00666153" w:rsidRPr="00512446" w:rsidRDefault="00666153" w:rsidP="004D7E1A"><w:pPr><w:widowControl w:val="0"/><w:suppressAutoHyphens/><w:autoSpaceDE w:val="0"/><w:autoSpaceDN w:val="0"/><w:jc w:val="both"/><w:rPr><w:rFonts w:ascii="Tahoma" w:eastAsia="Calibri" w:hAnsi="Tahoma" w:cs="Tahoma"/><w:bCs/><w:color w:val="000000"/></w:rPr></w:pPr><w:r w:rsidRPr="00512446"><w:rPr><w:rFonts w:ascii="Tahoma" w:eastAsia="Calibri" w:hAnsi="Tahoma" w:cs="Tahoma"/><w:bCs/><w:color w:val="000000"/></w:rPr><w:t>Составлен комиссией:</w:t></w:r></w:p></w:tc></w:tr><w:tr w:rsidR="00560093" w:rsidRPr="00512446" w14:paraId="54956FD3" w14:textId="77777777" w:rsidTr="000C7A08"><w:trPr><w:trHeight w:val="333"/></w:trPr><w:tc><w:tcPr><w:tcW w:w="2926" w:type="dxa"/><w:shd w:val="clear" w:color="auto" w:fill="auto"/></w:tcPr><w:p w14:paraId="221EAA90" w14:textId="77777777" w:rsidR="00560093" w:rsidRPr="00512446" w:rsidRDefault="00560093" w:rsidP="00A423B1"><w:pPr><w:suppressAutoHyphens/><w:autoSpaceDE w:val="0"/><w:autoSpaceDN w:val="0"/><w:ind w:left="-23" w:firstLine="12"/><w:rPr><w:rFonts w:ascii="Tahoma" w:eastAsia="Calibri" w:hAnsi="Tahoma" w:cs="Tahoma"/></w:rPr></w:pPr><w:r w:rsidRPr="00512446"><w:rPr><w:rFonts w:ascii="Tahoma" w:eastAsia="Calibri" w:hAnsi="Tahoma" w:cs="Tahoma"/><w:bCs/></w:rPr><w:t>Председатель</w:t></w:r><w:r w:rsidR="002A554D" w:rsidRPr="00512446"><w:rPr><w:rFonts w:ascii="Tahoma" w:eastAsia="Calibri" w:hAnsi="Tahoma" w:cs="Tahoma"/></w:rPr><w:t xml:space="preserve"> комиссии</w:t></w:r><w:r w:rsidRPr="00512446"><w:rPr><w:rFonts w:ascii="Tahoma" w:eastAsia="Calibri" w:hAnsi="Tahoma" w:cs="Tahoma"/></w:rPr><w:t>:</w:t></w:r></w:p></w:tc><w:tc><w:tcPr><w:tcW w:w="6662" w:type="dxa"/><w:shd w:val="clear" w:color="auto" w:fill="auto"/></w:tcPr><w:p w14:paraId="0D82236B" w14:textId="3F8BF29D" w:rsidR="00560093" w:rsidRPr="00EF48B6" w:rsidRDefault="00EF48B6" w:rsidP="0065760A"><w:pPr><w:suppressAutoHyphens/><w:autoSpaceDE w:val="0"/><w:autoSpaceDN w:val="0"/><w:jc w:val="both"/><w:rPr><w:rFonts w:ascii="Tahoma" w:eastAsia="Calibri" w:hAnsi="Tahoma" w:cs="Tahoma"/><w:bCs/><w:color w:val="000000"/><w:lang w:val="en-US"/></w:rPr></w:pPr><w:r w:rsidR="00CD17DF" w:rsidRPr="00CD17DF"><w:rPr><w:rFonts w:ascii="Tahoma" w:hAnsi="Tahoma" w:cs="Tahoma"/></w:rPr><w:t>words</w:t></w:r></w:p></w:tc></w:tr><w:tr w:rsidR="00560093" w:rsidRPr="00512446" w14:paraId="07D8BF05" w14:textId="77777777" w:rsidTr="000C7A08"><w:trPr><w:trHeight w:val="597"/></w:trPr><w:tc><w:tcPr><w:tcW w:w="2926" w:type="dxa"/><w:shd w:val="clear" w:color="auto" w:fill="auto"/></w:tcPr><w:p w14:paraId="03EFD516" w14:textId="77777777" w:rsidR="00560093" w:rsidRPr="00512446" w:rsidRDefault="00560093" w:rsidP="00A423B1"><w:pPr><w:tabs><w:tab w:val="left" w:pos="1843"/><w:tab w:val="left" w:pos="2410"/></w:tabs><w:ind w:left="-23" w:firstLine="12"/><w:jc w:val="both"/><w:rPr><w:rFonts w:ascii="Tahoma" w:eastAsia="Calibri" w:hAnsi="Tahoma" w:cs="Tahoma"/></w:rPr></w:pPr><w:r w:rsidRPr="00512446"><w:rPr><w:rFonts w:ascii="Tahoma" w:eastAsia="Calibri" w:hAnsi="Tahoma" w:cs="Tahoma"/></w:rPr><w:t>Члены комиссии:</w:t></w:r></w:p></w:tc><w:tc><w:tcPr><w:tcW w:w="6662" w:type="dxa"/><w:shd w:val="clear" w:color="auto" w:fill="auto"/></w:tcPr><w:p w14:paraId="2CCEC9BA" w14:textId="77777777" w:rsidR="00D81FDA" w:rsidRDefault="00EF48B6" w:rsidP="00D81FDA"><w:pPr><w:tabs><w:tab w:val="left" w:pos="-44"/><w:tab w:val="left" w:pos="882"/></w:tabs><w:suppressAutoHyphens/><w:autoSpaceDE w:val="0"/><w:autoSpaceDN w:val="0"/><w:adjustRightInd w:val="0"/><w:contextualSpacing/><w:jc w:val="both"/><w:rPr><w:rFonts w:ascii="Tahoma" w:hAnsi="Tahoma" w:cs="Tahoma"/></w:rPr></w:pPr><w:r w:rsidR="00CD17DF" w:rsidRPr="00CD17DF"><w:rPr><w:rFonts w:ascii="Tahoma" w:hAnsi="Tahoma" w:cs="Tahoma"/></w:rPr><w:t>words</w:t></w:r><w:proofErr w:type="gramEnd"/><w:r w:rsidR="00D82696" w:rsidRPr="00512446"><w:rPr><w:rFonts w:ascii="Tahoma" w:hAnsi="Tahoma" w:cs="Tahoma"/></w:rPr><w:t xml:space="preserve"> </w:t></w:r></w:p><w:p w14:paraId="628E4ACE" w14:textId="0623F731" w:rsidR="00EA3CBB" w:rsidRPr="00D81FDA" w:rsidRDefault="00FA0C51" w:rsidP="00D81FDA"><w:pPr><w:tabs><w:tab w:val="left" w:pos="-44"/><w:tab w:val="left" w:pos="882"/></w:tabs><w:suppressAutoHyphens/><w:autoSpaceDE w:val="0"/><w:autoSpaceDN w:val="0"/><w:adjustRightInd w:val="0"/><w:contextualSpacing/><w:jc w:val="both"/><w:rPr><w:rFonts w:ascii="Tahoma" w:hAnsi="Tahoma" w:cs="Tahoma"/></w:rPr></w:pPr><w:r w:rsidR="00CD17DF" w:rsidRPr="00CD17DF"><w:rPr><w:rFonts w:ascii="Tahoma" w:hAnsi="Tahoma" w:cs="Tahoma"/></w:rPr><w:t>words</w:t></w:r></w:p></w:tc></w:tr></w:tbl><w:p w14:paraId="2124D1CC" w14:textId="77777777" w:rsidR="00D52A1D" w:rsidRPr="00512446" w:rsidRDefault="00B84DFD" w:rsidP="00D52A1D"><w:pPr><w:widowControl w:val="0"/><w:tabs><w:tab w:val="num" w:pos="0"/></w:tabs><w:suppressAutoHyphens/><w:autoSpaceDE w:val="0"/><w:autoSpaceDN w:val="0"/><w:ind w:right="-2"/><w:jc w:val="both"/><w:rPr><w:rFonts w:ascii="Tahoma" w:hAnsi="Tahoma" w:cs="Tahoma"/></w:rPr></w:pPr><w:r w:rsidRPr="00512446"><w:rPr><w:rFonts w:ascii="Tahoma" w:hAnsi="Tahoma" w:cs="Tahoma"/></w:rPr><w:t xml:space="preserve">   </w:t></w:r></w:p><w:p w14:paraId="1C9154AE" w14:textId="56C5D076" w:rsidR="000C7A08" w:rsidRPr="000C7A08" w:rsidRDefault="001659AF" w:rsidP="000C7A08"><w:pPr><w:ind w:firstLine="708"/><w:jc w:val="both"/><w:rPr><w:rFonts w:ascii="Tahoma" w:hAnsi="Tahoma" w:cs="Tahoma"/><w:lang w:eastAsia="en-US"/></w:rPr></w:pPr><w:r w:rsidRPr="00512446"><w:rPr><w:rFonts w:ascii="Tahoma" w:hAnsi="Tahoma" w:cs="Tahoma"/></w:rPr><w:t xml:space="preserve">   </w:t></w:r><w:r w:rsidR="00CD17DF" w:rsidRPr="00CD17DF"><w:rPr><w:rFonts w:ascii="Tahoma" w:hAnsi="Tahoma" w:cs="Tahoma"/></w:rPr><w:t>words</w:t></w:r><w:r w:rsidR="00945422" w:rsidRPr="0065760A"><w:rPr><w:rFonts w:ascii="Tahoma" w:eastAsia="Calibri" w:hAnsi="Tahoma" w:cs="Tahoma"/><w:lang w:eastAsia="en-US"/></w:rPr><w:t xml:space="preserve"> в </w:t></w:r><w:r w:rsidR="00A423B1" w:rsidRPr="0065760A"><w:rPr><w:rFonts w:ascii="Tahoma" w:eastAsia="Calibri" w:hAnsi="Tahoma" w:cs="Tahoma"/><w:lang w:eastAsia="en-US"/></w:rPr><w:t xml:space="preserve">горной </w:t></w:r><w:r w:rsidR="00945422" w:rsidRPr="0065760A"><w:rPr><w:rFonts w:ascii="Tahoma" w:eastAsia="Calibri" w:hAnsi="Tahoma" w:cs="Tahoma"/><w:lang w:eastAsia="en-US"/></w:rPr><w:t xml:space="preserve">выработке </w:t></w:r><w:r w:rsidR="00B32969"><w:rPr><w:rFonts w:ascii="Tahoma" w:hAnsi="Tahoma" w:cs="Tahoma"/></w:rPr><w:t>РВ-2</w:t></w:r><w:r w:rsidR="000C7A08" w:rsidRPr="0065760A"><w:rPr><w:rFonts w:ascii="Tahoma" w:eastAsia="Calibri" w:hAnsi="Tahoma" w:cs="Tahoma"/><w:lang w:eastAsia="en-US"/></w:rPr><w:t xml:space="preserve"> рудника </w:t></w:r><w:r w:rsidR="003F1B7A"><w:rPr><w:rFonts w:ascii="Tahoma" w:hAnsi="Tahoma" w:cs="Tahoma"/></w:rPr><w:t>«</w:t></w:r><w:r w:rsidR="00B32969"><w:rPr><w:rFonts w:ascii="Tahoma" w:hAnsi="Tahoma" w:cs="Tahoma"/></w:rPr><w:t>Скалистый</w:t></w:r><w:r w:rsidR="003F1B7A"><w:rPr><w:rFonts w:ascii="Tahoma" w:hAnsi="Tahoma" w:cs="Tahoma"/></w:rPr><w:t>»</w:t></w:r><w:r w:rsidR="00A423B1" w:rsidRPr="0065760A"><w:rPr><w:rFonts w:ascii="Tahoma" w:eastAsia="Calibri" w:hAnsi="Tahoma" w:cs="Tahoma"/><w:lang w:eastAsia="en-US"/></w:rPr><w:t>,</w:t></w:r><w:r w:rsidR="000C7A08" w:rsidRPr="0065760A"><w:rPr><w:rFonts w:ascii="Tahoma" w:eastAsia="Calibri" w:hAnsi="Tahoma" w:cs="Tahoma"/><w:lang w:eastAsia="en-US"/></w:rPr><w:t xml:space="preserve"> в точке</w:t></w:r><w:r w:rsidR="00A423B1" w:rsidRPr="0065760A"><w:rPr><w:rFonts w:ascii="Tahoma" w:eastAsia="Calibri" w:hAnsi="Tahoma" w:cs="Tahoma"/><w:lang w:eastAsia="en-US"/></w:rPr><w:t xml:space="preserve"> с</w:t></w:r><w:r w:rsidR="00A423B1"><w:rPr><w:rFonts w:ascii="Tahoma" w:eastAsia="Calibri" w:hAnsi="Tahoma" w:cs="Tahoma"/><w:lang w:eastAsia="en-US"/></w:rPr><w:t xml:space="preserve"> координатами</w:t></w:r><w:r w:rsidR="000C7A08" w:rsidRPr="000C7A08"><w:rPr><w:rFonts w:ascii="Tahoma" w:eastAsia="Calibri" w:hAnsi="Tahoma" w:cs="Tahoma"/><w:lang w:eastAsia="en-US"/></w:rPr><w:t>:</w:t></w:r><m:oMath><m:r><w:rPr><w:rFonts w:ascii="Cambria Math" w:hAnsi="Cambria Math" w:cs="Tahoma"/></w:rPr><m:t xml:space="preserve"> </m:t></m:r><m:r><m:rPr><m:sty m:val="bi"/></m:rPr><w:rPr><w:rFonts w:ascii="Cambria Math" w:hAnsi="Cambria Math" w:cs="Tahoma"/></w:rPr><m:t>X=</m:t></m:r><m:r><w:rPr><w:rFonts w:ascii="Cambria Math" w:eastAsia="Calibri" w:hAnsi="Cambria Math" w:cs="Tahoma" /><w:lang w:eastAsia="en-US" /></w:rPr><m:t>1999</m:t></m:r></m:oMath><w:r w:rsidR="00245078" w:rsidRPr="000F3850"><w:rPr><w:rFonts w:ascii="Tahoma" w:eastAsia="Calibri" w:hAnsi="Tahoma" w:cs="Tahoma"/><w:lang w:eastAsia="en-US"/></w:rPr><w:t>,</w:t></w:r><w:r w:rsidR="00A423B1"><w:rPr><w:rFonts w:ascii="Tahoma" w:eastAsia="Calibri" w:hAnsi="Tahoma" w:cs="Tahoma"/><w:lang w:eastAsia="en-US"/></w:rPr><w:t xml:space="preserve"> </w:t></w:r><m:oMath><m:r><m:rPr><m:sty m:val="bi"/></m:rPr><w:rPr><w:rFonts w:ascii="Cambria Math" w:eastAsia="Calibri" w:hAnsi="Cambria Math" w:cs="Tahoma"/><w:lang w:eastAsia="en-US"/></w:rPr><m:t>Y=</m:t></m:r><m:r><w:rPr><w:rFonts w:ascii="Cambria Math" w:eastAsia="Calibri" w:hAnsi="Cambria Math" w:cs="Tahoma" /><w:lang w:eastAsia="en-US" /></w:rPr><m:t>1999</m:t></m:r></m:oMath><w:r w:rsidR="000C7A08" w:rsidRPr="000C7A08"><w:rPr><w:rFonts w:ascii="Tahoma" w:hAnsi="Tahoma" w:cs="Tahoma"/><w:lang w:eastAsia="en-US"/></w:rPr><w:t xml:space="preserve">, </w:t></w:r><m:oMath><m:r><m:rPr><m:sty m:val="bi"/></m:rPr><w:rPr><w:rFonts w:ascii="Cambria Math" w:hAnsi="Cambria Math" w:cs="Tahoma"/><w:lang w:eastAsia="en-US"/></w:rPr><m:t>Z=</m:t></m:r><m:r><w:rPr><w:rFonts w:ascii="Cambria Math" w:eastAsia="Calibri" w:hAnsi="Cambria Math" w:cs="Tahoma" /><w:lang w:eastAsia="en-US" /></w:rPr><m:t>1999</m:t></m:r></m:oMath><w:r w:rsidR="00A423B1"><w:rPr><w:rFonts w:ascii="Tahoma" w:eastAsiaTheme="minorEastAsia" w:hAnsi="Tahoma" w:cs="Tahoma"/><w:lang w:eastAsia="en-US"/></w:rPr><w:t xml:space="preserve">, </w:t></w:r><w:r w:rsidR="000C7A08"><w:rPr><w:rFonts w:ascii="Tahoma" w:eastAsiaTheme="minorEastAsia" w:hAnsi="Tahoma" w:cs="Tahoma"/><w:lang w:eastAsia="en-US"/></w:rPr><w:t>были произведены замеры категории удароопасности</w:t></w:r><w:r w:rsidR="000C7A08" w:rsidRPr="000C7A08"><w:rPr><w:rFonts w:ascii="Tahoma" w:hAnsi="Tahoma" w:cs="Tahoma"/><w:lang w:eastAsia="en-US"/></w:rPr><w:t>.</w:t></w:r></w:p><w:p w14:paraId="0E6A5B53" w14:textId="77777777" w:rsidR="000C7A08" w:rsidRPr="000C7A08" w:rsidRDefault="000C7A08" w:rsidP="002E44E6"><w:pPr><w:ind w:firstLine="709"/><w:jc w:val="both"/><w:rPr><w:rFonts w:ascii="Tahoma" w:eastAsia="Calibri" w:hAnsi="Tahoma" w:cs="Tahoma"/><w:lang w:eastAsia="en-US"/></w:rPr></w:pPr><w:r w:rsidRPr="000C7A08"><w:rPr><w:rFonts w:ascii="Tahoma" w:eastAsia="Calibri" w:hAnsi="Tahoma" w:cs="Tahoma"/><w:lang w:eastAsia="en-US"/></w:rPr><w:t>Категория удароопасности определялась инструментал</w:t></w:r><w:r w:rsidR="00A423B1"><w:rPr><w:rFonts w:ascii="Tahoma" w:eastAsia="Calibri" w:hAnsi="Tahoma" w:cs="Tahoma"/><w:lang w:eastAsia="en-US"/></w:rPr><w:t>ьным методом</w:t></w:r><w:r w:rsidR="009D259D"><w:rPr><w:rFonts w:ascii="Tahoma" w:eastAsia="Calibri" w:hAnsi="Tahoma" w:cs="Tahoma"/><w:lang w:eastAsia="en-US"/></w:rPr><w:t>,</w:t></w:r><w:r w:rsidR="00A423B1"><w:rPr><w:rFonts w:ascii="Tahoma" w:eastAsia="Calibri" w:hAnsi="Tahoma" w:cs="Tahoma"/><w:lang w:eastAsia="en-US"/></w:rPr><w:t xml:space="preserve"> согласно приложению</w:t></w:r><w:r w:rsidRPr="000C7A08"><w:rPr><w:rFonts w:ascii="Tahoma" w:eastAsia="Calibri" w:hAnsi="Tahoma" w:cs="Tahoma"/><w:lang w:eastAsia="en-US"/></w:rPr><w:t xml:space="preserve"> №</w:t></w:r><w:r w:rsidR="00A423B1"><w:rPr><w:rFonts w:ascii="Tahoma" w:eastAsia="Calibri" w:hAnsi="Tahoma" w:cs="Tahoma"/><w:lang w:eastAsia="en-US"/></w:rPr><w:t xml:space="preserve"> </w:t></w:r><w:r w:rsidRPr="000C7A08"><w:rPr><w:rFonts w:ascii="Tahoma" w:eastAsia="Calibri" w:hAnsi="Tahoma" w:cs="Tahoma"/><w:lang w:eastAsia="en-US"/></w:rPr><w:t xml:space="preserve">8 </w:t></w:r><w:r w:rsidR="00A423B1"><w:rPr><w:rFonts w:ascii="Tahoma" w:eastAsia="Calibri" w:hAnsi="Tahoma" w:cs="Tahoma"/><w:lang w:eastAsia="en-US"/></w:rPr><w:t>«</w:t></w:r><w:r w:rsidRPr="000C7A08"><w:rPr><w:rFonts w:ascii="Tahoma" w:eastAsia="Calibri" w:hAnsi="Tahoma" w:cs="Tahoma"/><w:lang w:eastAsia="en-US"/></w:rPr><w:t>Указаний по безопасному ведению горных работ на Талнахском и Октябрьском месторождениях, склонных и опасных по горным ударам»</w:t></w:r><w:r w:rsidR="009D259D"><w:rPr><w:rFonts w:ascii="Tahoma" w:eastAsia="Calibri" w:hAnsi="Tahoma" w:cs="Tahoma"/><w:lang w:eastAsia="en-US"/></w:rPr><w:t>,</w:t></w:r><w:r w:rsidRPr="000C7A08"><w:rPr><w:rFonts w:ascii="Tahoma" w:eastAsia="Calibri" w:hAnsi="Tahoma" w:cs="Tahoma"/><w:lang w:eastAsia="en-US"/></w:rPr><w:t xml:space="preserve"> по «Методике прогноза степени удароопасности массива горных пород экспресс – методом с помощью приборов «Прогноз-М (1М), «Ангел</w:t></w:r><w:r w:rsidR="002E44E6" w:rsidRPr="000C7A08"><w:rPr><w:rFonts w:ascii="Tahoma" w:eastAsia="Calibri" w:hAnsi="Tahoma" w:cs="Tahoma"/><w:lang w:eastAsia="en-US"/></w:rPr><w:t>»</w:t></w:r><w:r w:rsidRPr="000C7A08"><w:rPr><w:rFonts w:ascii="Tahoma" w:eastAsia="Calibri" w:hAnsi="Tahoma" w:cs="Tahoma"/><w:lang w:eastAsia="en-US"/></w:rPr><w:t xml:space="preserve"> (или аналогичными)</w:t></w:r><w:r w:rsidR="009D259D"><w:rPr><w:rFonts w:ascii="Tahoma" w:eastAsia="Calibri" w:hAnsi="Tahoma" w:cs="Tahoma"/><w:lang w:eastAsia="en-US"/></w:rPr><w:t>»</w:t></w:r><w:r w:rsidRPr="000C7A08"><w:rPr><w:rFonts w:ascii="Tahoma" w:eastAsia="Calibri" w:hAnsi="Tahoma" w:cs="Tahoma"/><w:lang w:eastAsia="en-US"/></w:rPr><w:t>.</w:t></w:r></w:p><w:p w14:paraId="213E36E7" w14:textId="2C5E7360" w:rsidR="000C7A08" w:rsidRPr="000C7A08" w:rsidRDefault="000C7A08" w:rsidP="003A458E"><w:pPr><w:ind w:firstLine="709"/><w:jc w:val="both"/><w:rPr><w:rFonts w:ascii="Tahoma" w:eastAsia="Calibri" w:hAnsi="Tahoma" w:cs="Tahoma"/><w:lang w:eastAsia="en-US"/></w:rPr></w:pPr><w:r w:rsidRPr="000C7A08"><w:rPr><w:rFonts w:ascii="Tahoma" w:eastAsia="Calibri" w:hAnsi="Tahoma" w:cs="Tahoma"/><w:lang w:eastAsia="en-US"/></w:rPr><w:t xml:space="preserve">Параметры, характеризующие степень удароопасности исследуемого участка массива горных пород, определялись на основе интерпретации графика зависимости параметра </w:t></w:r><m:oMath><m:r><w:rPr><w:rFonts w:ascii="Cambria Math" w:eastAsia="Calibri" w:hAnsi="Cambria Math" w:cs="Tahoma"/><w:lang w:eastAsia="en-US"/></w:rPr><m:t>N</m:t></m:r></m:oMath><w:r w:rsidRPr="000C7A08"><w:rPr><w:rFonts w:ascii="Tahoma" w:eastAsia="Calibri" w:hAnsi="Tahoma" w:cs="Tahoma"/><w:lang w:eastAsia="en-US"/></w:rPr><w:t xml:space="preserve"> от глубины подвигающего забоя шпура</w:t></w:r><w:r w:rsidR="009D259D"><w:rPr><w:rFonts w:ascii="Tahoma" w:eastAsia="Calibri" w:hAnsi="Tahoma" w:cs="Tahoma"/><w:lang w:eastAsia="en-US"/></w:rPr><w:t>,</w:t></w:r><w:r w:rsidRPr="000C7A08"><w:rPr><w:rFonts w:ascii="Tahoma" w:eastAsia="Calibri" w:hAnsi="Tahoma" w:cs="Tahoma"/><w:lang w:eastAsia="en-US"/></w:rPr><w:t xml:space="preserve"> полученного по р</w:t></w:r><w:r><w:rPr><w:rFonts w:ascii="Tahoma" w:eastAsia="Calibri" w:hAnsi="Tahoma" w:cs="Tahoma"/><w:lang w:eastAsia="en-US"/></w:rPr><w:t>езультатам измерений (рисунок 1</w:t></w:r><w:r w:rsidRPr="000C7A08"><w:rPr><w:rFonts w:ascii="Tahoma" w:eastAsia="Calibri" w:hAnsi="Tahoma" w:cs="Tahoma"/><w:lang w:eastAsia="en-US"/></w:rPr><w:t>а). Скорость подвигания забоя шпура в процессе бурения принимается постоянной с отклонением в ту или иную сторону не более 15</w:t></w:r><w:r w:rsidR="009D259D"><w:rPr><w:rFonts w:ascii="Tahoma" w:eastAsia="Calibri" w:hAnsi="Tahoma" w:cs="Tahoma"/><w:lang w:eastAsia="en-US"/></w:rPr><w:t xml:space="preserve"> </w:t></w:r><w:r w:rsidRPr="000C7A08"><w:rPr><w:rFonts w:ascii="Tahoma" w:eastAsia="Calibri" w:hAnsi="Tahoma" w:cs="Tahoma"/><w:lang w:eastAsia="en-US"/></w:rPr><w:t xml:space="preserve">%. Расстояние до максимума опорного давления </w:t></w:r><m:oMath><m:sSub><m:sSubPr><m:ctrlPr><w:rPr><w:rFonts w:ascii="Cambria Math" w:eastAsia="Calibri" w:hAnsi="Cambria Math" w:cs="Tahoma"/><w:i/><w:lang w:eastAsia="en-US"/></w:rPr></m:ctrlPr></m:sSubPr><m:e><m:r><w:rPr><w:rFonts w:ascii="Cambria Math" w:eastAsia="Calibri" w:hAnsi="Cambria Math" w:cs="Tahoma"/><w:lang w:eastAsia="en-US"/></w:rPr><m:t>X</m:t></m:r></m:e><m:sub><m:r><w:rPr><w:rFonts w:ascii="Cambria Math" w:eastAsia="Calibri" w:hAnsi="Cambria Math" w:cs="Tahoma"/><w:lang w:eastAsia="en-US"/></w:rPr><m:t>м</m:t></m:r></m:sub></m:sSub><m:r><w:rPr><w:rFonts w:ascii="Cambria Math" w:eastAsia="Calibri" w:hAnsi="Cambria Math" w:cs="Tahoma"/><w:lang w:eastAsia="en-US"/></w:rPr><m:t>=</m:t></m:r><m:r><w:rPr><w:rFonts w:ascii="Cambria Math" w:eastAsia="Calibri" w:hAnsi="Cambria Math" w:cs="Tahoma" /><w:lang w:eastAsia="en-US" /></w:rPr><m:t>1999</m:t></m:r></m:oMath><w:r w:rsidRPr="000C7A08"><w:rPr><w:rFonts w:ascii="Tahoma" w:eastAsia="Calibri" w:hAnsi="Tahoma" w:cs="Tahoma"/><w:lang w:eastAsia="en-US"/></w:rPr><w:t xml:space="preserve"> принимается равным глубине шпура на момент регистрации максимальной </w:t></w:r><w:r w:rsidRPr="000C7A08"><w:rPr><w:rFonts w:ascii="Tahoma" w:eastAsia="Calibri" w:hAnsi="Tahoma" w:cs="Tahoma"/><w:lang w:eastAsia="en-US"/></w:rPr><w:lastRenderedPageBreak/><w:t xml:space="preserve">интенсивности </w:t></w:r><m:oMath><m:sSub><m:sSubPr><m:ctrlPr><w:rPr><w:rFonts w:ascii="Cambria Math" w:eastAsia="Calibri" w:hAnsi="Cambria Math" w:cs="Tahoma"/><w:i/><w:lang w:eastAsia="en-US"/></w:rPr></m:ctrlPr></m:sSubPr><m:e><m:r><w:rPr><w:rFonts w:ascii="Cambria Math" w:eastAsia="Calibri" w:hAnsi="Cambria Math" w:cs="Tahoma"/><w:lang w:val="en-US" w:eastAsia="en-US"/></w:rPr><m:t>N</m:t></m:r></m:e><m:sub><m:r><w:rPr><w:rFonts w:ascii="Cambria Math" w:eastAsia="Calibri" w:hAnsi="Cambria Math" w:cs="Tahoma"/><w:lang w:eastAsia="en-US"/></w:rPr><m:t>max</m:t></m:r></m:sub></m:sSub></m:oMath><w:r w:rsidRPr="000C7A08"><w:rPr><w:rFonts w:ascii="Tahoma" w:hAnsi="Tahoma" w:cs="Tahoma"/><w:lang w:eastAsia="en-US"/></w:rPr><w:t xml:space="preserve"> </w:t></w:r><w:r w:rsidRPr="000C7A08"><w:rPr><w:rFonts w:ascii="Tahoma" w:eastAsia="Calibri" w:hAnsi="Tahoma" w:cs="Tahoma"/><w:lang w:eastAsia="en-US"/></w:rPr><w:t xml:space="preserve">вибросейсмического сигнала (по результатам измерений </w:t></w:r><m:oMath><m:sSub><m:sSubPr><m:ctrlPr><w:rPr><w:rFonts w:ascii="Cambria Math" w:eastAsia="Calibri" w:hAnsi="Cambria Math" w:cs="Tahoma"/><w:i/><w:lang w:eastAsia="en-US"/></w:rPr></m:ctrlPr></m:sSubPr><m:e><m:r><w:rPr><w:rFonts w:ascii="Cambria Math" w:eastAsia="Calibri" w:hAnsi="Cambria Math" w:cs="Tahoma"/><w:lang w:val="en-US" w:eastAsia="en-US"/></w:rPr><m:t>N</m:t></m:r></m:e><m:sub><m:r><w:rPr><w:rFonts w:ascii="Cambria Math" w:eastAsia="Calibri" w:hAnsi="Cambria Math" w:cs="Tahoma"/><w:lang w:eastAsia="en-US"/></w:rPr><m:t>max</m:t></m:r></m:sub></m:sSub><m:r><w:rPr><w:rFonts w:ascii="Cambria Math" w:eastAsia="Calibri" w:hAnsi="Cambria Math" w:cs="Tahoma"/><w:lang w:eastAsia="en-US"/></w:rPr><m:t>=</m:t></m:r><m:r><w:rPr><w:rFonts w:ascii="Cambria Math" w:eastAsia="Calibri" w:hAnsi="Cambria Math" w:cs="Tahoma" /><w:lang w:eastAsia="en-US" /></w:rPr><m:t>1999</m:t></m:r></m:oMath><w:r w:rsidRPr="000C7A08"><w:rPr><w:rFonts w:ascii="Tahoma" w:eastAsia="Calibri" w:hAnsi="Tahoma" w:cs="Tahoma"/><w:lang w:eastAsia="en-US"/></w:rPr><w:t>). В качестве относительной характеристики интенсивности нагрузок в зоне максимума используется отношение:</w:t></w:r></w:p><w:p w14:paraId="6ACCF4C9" w14:textId="608ACC8E" w:rsidR="000C7A08" w:rsidRPr="00DD2356" w:rsidRDefault="000741BB" w:rsidP="002E44E6"><w:pPr><w:ind w:firstLine="709"/><w:jc w:val="center"/><w:rPr><w:rFonts w:ascii="Tahoma" w:eastAsia="Calibri" w:hAnsi="Tahoma" w:cs="Tahoma"/><w:lang w:eastAsia="en-US"/></w:rPr></w:pPr><m:oMathPara><m:oMath><m:f><m:fPr><m:ctrlPr><w:rPr><w:rFonts w:ascii="Cambria Math" w:eastAsia="Calibri" w:hAnsi="Cambria Math" w:cs="Tahoma"/><w:i/><w:lang w:eastAsia="en-US"/></w:rPr></m:ctrlPr></m:fPr><m:num><m:sSub><m:sSubPr><m:ctrlPr><w:rPr><w:rFonts w:ascii="Cambria Math" w:eastAsia="Calibri" w:hAnsi="Cambria Math" w:cs="Tahoma"/><w:i/><w:lang w:eastAsia="en-US"/></w:rPr></m:ctrlPr></m:sSubPr><m:e><m:r><w:rPr><w:rFonts w:ascii="Cambria Math" w:eastAsia="Calibri" w:hAnsi="Cambria Math" w:cs="Tahoma"/><w:lang w:val="en-US" w:eastAsia="en-US"/></w:rPr><m:t>N</m:t></m:r></m:e><m:sub><m:r><w:rPr><w:rFonts w:ascii="Cambria Math" w:eastAsia="Calibri" w:hAnsi="Cambria Math" w:cs="Tahoma"/><w:lang w:val="en-US" w:eastAsia="en-US"/></w:rPr><m:t>max</m:t></m:r></m:sub></m:sSub></m:num><m:den><m:sSub><m:sSubPr><m:ctrlPr><w:rPr><w:rFonts w:ascii="Cambria Math" w:eastAsia="Calibri" w:hAnsi="Cambria Math" w:cs="Tahoma"/><w:i/><w:lang w:eastAsia="en-US"/></w:rPr></m:ctrlPr></m:sSubPr><m:e><m:r><w:rPr><w:rFonts w:ascii="Cambria Math" w:eastAsia="Calibri" w:hAnsi="Cambria Math" w:cs="Tahoma"/><w:lang w:eastAsia="en-US"/></w:rPr><m:t>N</m:t></m:r></m:e><m:sub><m:r><w:rPr><w:rFonts w:ascii="Cambria Math" w:eastAsia="Calibri" w:hAnsi="Cambria Math" w:cs="Tahoma"/><w:lang w:eastAsia="en-US"/></w:rPr><m:t>0</m:t></m:r></m:sub></m:sSub></m:den></m:f><m:r><w:rPr><w:rFonts w:ascii="Cambria Math" w:eastAsia="Calibri" w:hAnsi="Cambria Math" w:cs="Tahoma"/><w:lang w:eastAsia="en-US"/></w:rPr><m:t>=</m:t></m:r><m:f><m:fPr><m:ctrlPr><w:rPr><w:rFonts w:ascii="Cambria Math" w:eastAsia="Calibri" w:hAnsi="Cambria Math" w:cs="Tahoma"/><w:i/><w:lang w:val="en-US" w:eastAsia="en-US"/></w:rPr></m:ctrlPr></m:fPr><m:num><m:r><w:rPr><w:rFonts w:ascii="Cambria Math" w:eastAsia="Calibri" w:hAnsi="Cambria Math" w:cs="Tahoma" /><w:lang w:eastAsia="en-US" /></w:rPr><m:t>1999</m:t></m:r></m:num><m:den><m:r><w:rPr><w:rFonts w:ascii="Cambria Math" w:eastAsia="Calibri" w:hAnsi="Cambria Math" w:cs="Tahoma" /><w:lang w:eastAsia="en-US" /></w:rPr><m:t>1999</m:t></m:r></m:den></m:f><m:r><w:rPr><w:rFonts w:ascii="Cambria Math" w:eastAsia="Calibri" w:hAnsi="Cambria Math" w:cs="Tahoma"/><w:lang w:eastAsia="en-US"/></w:rPr><m:t>=</m:t></m:r><m:r><w:rPr><w:rFonts w:ascii="Cambria Math" w:eastAsia="Calibri" w:hAnsi="Cambria Math" w:cs="Tahoma" /><w:lang w:eastAsia="en-US" /></w:rPr><m:t>1999</m:t></m:r></m:oMath></m:oMathPara></w:p><w:p w14:paraId="53D7BE0D" w14:textId="442D8B1F" w:rsidR="000C7A08" w:rsidRPr="000C7A08" w:rsidRDefault="000C7A08" w:rsidP="003A458E"><w:pPr><w:ind w:firstLine="709"/><w:jc w:val="both"/><w:rPr><w:rFonts w:ascii="Tahoma" w:eastAsia="Calibri" w:hAnsi="Tahoma" w:cs="Tahoma"/><w:lang w:eastAsia="en-US"/></w:rPr></w:pPr><w:r w:rsidRPr="000C7A08"><w:rPr><w:rFonts w:ascii="Tahoma" w:eastAsia="Calibri" w:hAnsi="Tahoma" w:cs="Tahoma"/><w:lang w:eastAsia="en-US"/></w:rPr><w:t xml:space="preserve">где: </w:t></w:r><m:oMath><m:sSub><m:sSubPr><m:ctrlPr><w:rPr><w:rFonts w:ascii="Cambria Math" w:eastAsia="Calibri" w:hAnsi="Cambria Math" w:cs="Tahoma"/><w:i/><w:lang w:eastAsia="en-US"/></w:rPr></m:ctrlPr></m:sSubPr><m:e><m:r><w:rPr><w:rFonts w:ascii="Cambria Math" w:eastAsia="Calibri" w:hAnsi="Cambria Math" w:cs="Tahoma"/><w:lang w:eastAsia="en-US"/></w:rPr><m:t>N</m:t></m:r></m:e><m:sub><m:r><w:rPr><w:rFonts w:ascii="Cambria Math" w:eastAsia="Calibri" w:hAnsi="Cambria Math" w:cs="Tahoma"/><w:lang w:eastAsia="en-US"/></w:rPr><m:t>0</m:t></m:r></m:sub></m:sSub></m:oMath><w:r w:rsidRPr="000C7A08"><w:rPr><w:rFonts w:ascii="Tahoma" w:eastAsia="Calibri" w:hAnsi="Tahoma" w:cs="Tahoma"/><w:lang w:eastAsia="en-US"/></w:rPr><w:t xml:space="preserve"> – величина интенсивности вибросейсмического сигнала на контуре выработки (по результатам измерений </w:t></w:r><m:oMath><m:sSub><m:sSubPr><m:ctrlPr><w:rPr><w:rFonts w:ascii="Cambria Math" w:eastAsia="Calibri" w:hAnsi="Cambria Math" w:cs="Tahoma"/><w:i/><w:lang w:eastAsia="en-US"/></w:rPr></m:ctrlPr></m:sSubPr><m:e><m:r><w:rPr><w:rFonts w:ascii="Cambria Math" w:eastAsia="Calibri" w:hAnsi="Cambria Math" w:cs="Tahoma"/><w:lang w:eastAsia="en-US"/></w:rPr><m:t>N</m:t></m:r></m:e><m:sub><m:r><w:rPr><w:rFonts w:ascii="Cambria Math" w:eastAsia="Calibri" w:hAnsi="Cambria Math" w:cs="Tahoma"/><w:lang w:eastAsia="en-US"/></w:rPr><m:t>0</m:t></m:r></m:sub></m:sSub><m:r><w:rPr><w:rFonts w:ascii="Cambria Math" w:eastAsia="Calibri" w:hAnsi="Cambria Math" w:cs="Tahoma"/><w:lang w:eastAsia="en-US"/></w:rPr><m:t>=</m:t></m:r><m:r><w:rPr><w:rFonts w:ascii="Cambria Math" w:eastAsia="Calibri" w:hAnsi="Cambria Math" w:cs="Tahoma" /><w:lang w:eastAsia="en-US" /></w:rPr><m:t>1999</m:t></m:r></m:oMath><w:r w:rsidRPr="000C7A08"><w:rPr><w:rFonts w:ascii="Tahoma" w:eastAsia="Calibri" w:hAnsi="Tahoma" w:cs="Tahoma"/><w:lang w:eastAsia="en-US"/></w:rPr><w:t>).</w:t></w:r></w:p><w:p w14:paraId="16A2DC74" w14:textId="6A97ECDF" w:rsidR="000C7A08" w:rsidRDefault="000C7A08" w:rsidP="002E44E6"><w:pPr><w:ind w:firstLine="709"/><w:jc w:val="both"/><w:rPr><w:rFonts w:ascii="Tahoma" w:eastAsia="Calibri" w:hAnsi="Tahoma" w:cs="Tahoma"/><w:lang w:eastAsia="en-US"/></w:rPr></w:pPr><w:r w:rsidRPr="000C7A08"><w:rPr><w:rFonts w:ascii="Tahoma" w:eastAsia="Calibri" w:hAnsi="Tahoma" w:cs="Tahoma"/><w:lang w:eastAsia="en-US"/></w:rPr><w:t xml:space="preserve">Степень удароопасности исследуемого массива горных пород определяется по положению точки с координатами </w:t></w:r><m:oMath><m:f><m:fPr><m:type m:val="lin"/><m:ctrlPr><w:rPr><w:rFonts w:ascii="Cambria Math" w:eastAsia="Calibri" w:hAnsi="Cambria Math" w:cs="Tahoma"/><w:i/><w:lang w:eastAsia="en-US"/></w:rPr></m:ctrlPr></m:fPr><m:num><m:sSub><m:sSubPr><m:ctrlPr><w:rPr><w:rFonts w:ascii="Cambria Math" w:eastAsia="Calibri" w:hAnsi="Cambria Math" w:cs="Tahoma"/><w:i/><w:lang w:eastAsia="en-US"/></w:rPr></m:ctrlPr></m:sSubPr><m:e><m:r><w:rPr><w:rFonts w:ascii="Cambria Math" w:eastAsia="Calibri" w:hAnsi="Cambria Math" w:cs="Tahoma"/><w:lang w:eastAsia="en-US"/></w:rPr><m:t>X</m:t></m:r></m:e><m:sub><m:r><w:rPr><w:rFonts w:ascii="Cambria Math" w:eastAsia="Calibri" w:hAnsi="Cambria Math" w:cs="Tahoma"/><w:lang w:eastAsia="en-US"/></w:rPr><m:t>м</m:t></m:r></m:sub></m:sSub></m:num><m:den><m:r><w:rPr><w:rFonts w:ascii="Cambria Math" w:eastAsia="Calibri" w:hAnsi="Cambria Math" w:cs="Tahoma"/><w:lang w:eastAsia="en-US"/></w:rPr><m:t>h</m:t></m:r></m:den></m:f><m:r><w:rPr><w:rFonts w:ascii="Cambria Math" w:eastAsia="Calibri" w:hAnsi="Cambria Math" w:cs="Tahoma"/><w:lang w:eastAsia="en-US"/></w:rPr><m:t>=</m:t></m:r><m:r><w:rPr><w:rFonts w:ascii="Cambria Math" w:eastAsia="Calibri" w:hAnsi="Cambria Math" w:cs="Tahoma" /><w:lang w:eastAsia="en-US" /></w:rPr><m:t>1999</m:t></m:r></m:oMath><w:r w:rsidR="001455E7" w:rsidRPr="00403B81"><w:rPr><w:rFonts w:ascii="Tahoma" w:eastAsia="Calibri" w:hAnsi="Tahoma" w:cs="Tahoma"/><w:lang w:eastAsia="en-US"/></w:rPr><w:t xml:space="preserve"> </w:t></w:r><w:r w:rsidRPr="000C7A08"><w:rPr><w:rFonts w:ascii="Tahoma" w:eastAsia="Calibri" w:hAnsi="Tahoma" w:cs="Tahoma"/><w:lang w:eastAsia="en-US"/></w:rPr><w:t xml:space="preserve">и </w:t></w:r><m:oMath><m:f><m:fPr><m:type m:val="lin"/><m:ctrlPr><w:rPr><w:rFonts w:ascii="Cambria Math" w:eastAsia="Calibri" w:hAnsi="Cambria Math" w:cs="Tahoma"/><w:i/><w:lang w:eastAsia="en-US"/></w:rPr></m:ctrlPr></m:fPr><m:num><m:sSub><m:sSubPr><m:ctrlPr><w:rPr><w:rFonts w:ascii="Cambria Math" w:eastAsia="Calibri" w:hAnsi="Cambria Math" w:cs="Tahoma"/><w:i/><w:lang w:eastAsia="en-US"/></w:rPr></m:ctrlPr></m:sSubPr><m:e><m:r><w:rPr><w:rFonts w:ascii="Cambria Math" w:eastAsia="Calibri" w:hAnsi="Cambria Math" w:cs="Tahoma"/><w:lang w:val="en-US" w:eastAsia="en-US"/></w:rPr><m:t>N</m:t></m:r></m:e><m:sub><m:r><w:rPr><w:rFonts w:ascii="Cambria Math" w:eastAsia="Calibri" w:hAnsi="Cambria Math" w:cs="Tahoma"/><w:lang w:eastAsia="en-US"/></w:rPr><m:t>max</m:t></m:r></m:sub></m:sSub></m:num><m:den><m:sSub><m:sSubPr><m:ctrlPr><w:rPr><w:rFonts w:ascii="Cambria Math" w:eastAsia="Calibri" w:hAnsi="Cambria Math" w:cs="Tahoma"/><w:i/><w:lang w:eastAsia="en-US"/></w:rPr></m:ctrlPr></m:sSubPr><m:e><m:r><w:rPr><w:rFonts w:ascii="Cambria Math" w:eastAsia="Calibri" w:hAnsi="Cambria Math" w:cs="Tahoma"/><w:lang w:eastAsia="en-US"/></w:rPr><m:t>N</m:t></m:r></m:e><m:sub><m:r><w:rPr><w:rFonts w:ascii="Cambria Math" w:eastAsia="Calibri" w:hAnsi="Cambria Math" w:cs="Tahoma"/><w:lang w:eastAsia="en-US"/></w:rPr><m:t>0</m:t></m:r></m:sub></m:sSub><m:r><w:rPr><w:rFonts w:ascii="Cambria Math" w:eastAsia="Calibri" w:hAnsi="Cambria Math" w:cs="Tahoma"/><w:lang w:eastAsia="en-US"/></w:rPr><m:t>=</m:t></m:r></m:den></m:f><m:r><w:rPr><w:rFonts w:ascii="Cambria Math" w:eastAsia="Calibri" w:hAnsi="Cambria Math" w:cs="Tahoma" /><w:lang w:eastAsia="en-US" /></w:rPr><m:t>1999</m:t></m:r></m:oMath><w:r w:rsidR="001455E7" w:rsidRPr="001455E7"><w:rPr><w:rFonts w:ascii="Tahoma" w:eastAsia="Calibri" w:hAnsi="Tahoma" w:cs="Tahoma"/><w:lang w:eastAsia="en-US"/></w:rPr><w:t xml:space="preserve"> </w:t></w:r><w:r w:rsidRPr="000C7A08"><w:rPr><w:rFonts w:ascii="Tahoma" w:eastAsia="Calibri" w:hAnsi="Tahoma" w:cs="Tahoma"/><w:lang w:eastAsia="en-US"/></w:rPr><w:t>в области изменения параметров вибросейсмического сигнала (рисунок 1</w:t></w:r><w:r><w:rPr><w:rFonts w:ascii="Tahoma" w:eastAsia="Calibri" w:hAnsi="Tahoma" w:cs="Tahoma"/><w:lang w:eastAsia="en-US"/></w:rPr><w:t>б</w:t></w:r><w:r w:rsidRPr="000C7A08"><w:rPr><w:rFonts w:ascii="Tahoma" w:eastAsia="Calibri" w:hAnsi="Tahoma" w:cs="Tahoma"/><w:lang w:eastAsia="en-US"/></w:rPr><w:t xml:space="preserve">) где: </w:t></w:r><m:oMath><m:r><w:rPr><w:rFonts w:ascii="Cambria Math" w:eastAsia="Calibri" w:hAnsi="Cambria Math" w:cs="Tahoma"/><w:lang w:eastAsia="en-US"/></w:rPr><m:t>h</m:t></m:r></m:oMath><w:r w:rsidRPr="000C7A08"><w:rPr><w:rFonts w:ascii="Tahoma" w:eastAsia="Calibri" w:hAnsi="Tahoma" w:cs="Tahoma"/><w:lang w:eastAsia="en-US"/></w:rPr><w:t xml:space="preserve"> – высота выработки в месте выполнения измерений (</w:t></w:r><m:oMath><m:r><w:rPr><w:rFonts w:ascii="Cambria Math" w:eastAsia="Calibri" w:hAnsi="Cambria Math" w:cs="Tahoma"/><w:lang w:eastAsia="en-US"/></w:rPr><m:t>h=</m:t></m:r><m:r><w:rPr><w:rFonts w:ascii="Cambria Math" w:eastAsia="Calibri" w:hAnsi="Cambria Math" w:cs="Tahoma" /><w:lang w:eastAsia="en-US" /></w:rPr><m:t>1999</m:t></m:r></m:oMath><w:r w:rsidRPr="000C7A08"><w:rPr><w:rFonts w:ascii="Tahoma" w:eastAsia="Calibri" w:hAnsi="Tahoma" w:cs="Tahoma"/><w:lang w:eastAsia="en-US"/></w:rPr><w:t>).</w:t></w:r></w:p><w:p w14:paraId="00F01EEB" w14:textId="77777777" w:rsidR="002E44E6" w:rsidRDefault="002E44E6" w:rsidP="002E44E6"><w:pPr><w:ind w:firstLine="709"/><w:jc w:val="both"/><w:rPr><w:rFonts w:ascii="Tahoma" w:eastAsia="Calibri" w:hAnsi="Tahoma" w:cs="Tahoma"/><w:lang w:eastAsia="en-US"/></w:rPr></w:pPr></w:p><w:tbl><w:tblPr><w:tblStyle w:val="a7"/><w:tblW w:w="0" w:type="auto"/><w:tblBorders><w:top w:val="none" w:sz="0" w:space="0" w:color="auto"/><w:left w:val="none" w:sz="0" w:space="0" w:color="auto"/><w:bottom w:val="none" w:sz="0" w:space="0" w:color="auto"/><w:right w:val="none" w:sz="0" w:space="0" w:color="auto"/><w:insideH w:val="none" w:sz="0" w:space="0" w:color="auto"/><w:insideV w:val="none" w:sz="0" w:space="0" w:color="auto"/></w:tblBorders><w:tblLook w:val="04A0" w:firstRow="1" w:lastRow="0" w:firstColumn="1" w:lastColumn="0" w:noHBand="0" w:noVBand="1"/></w:tblPr><w:tblGrid><w:gridCol w:w="5985"/><w:gridCol w:w="3086"/></w:tblGrid><w:tr w:rsidR="000C7A08" w14:paraId="22E93E79" w14:textId="77777777" w:rsidTr="000C7A08"><w:tc><w:tcPr><w:tcW w:w="6204" w:type="dxa"/></w:tcPr><w:p w14:paraId="16DEC982" w14:textId="77777777" w:rsidR="000C7A08" w:rsidRDefault="000C7A08" w:rsidP="000C7A08"><w:pPr><w:spacing w:after="160" w:line="259" w:lineRule="auto"/><w:jc w:val="both"/><w:rPr><w:rFonts w:ascii="Tahoma" w:hAnsi="Tahoma" w:cs="Tahoma"/></w:rPr></w:pPr><w:r><w:rPr><w:rFonts w:ascii="Tahoma" w:hAnsi="Tahoma" w:cs="Tahoma"/></w:rPr><w:t>а)</w:t></w:r></w:p></w:tc><w:tc><w:tcPr><w:tcW w:w="3650" w:type="dxa"/></w:tcPr><w:p w14:paraId="7BE5332D" w14:textId="77777777" w:rsidR="000C7A08" w:rsidRDefault="000C7A08" w:rsidP="000C7A08"><w:pPr><w:spacing w:after="160" w:line="259" w:lineRule="auto"/><w:jc w:val="both"/><w:rPr><w:rFonts w:ascii="Tahoma" w:hAnsi="Tahoma" w:cs="Tahoma"/></w:rPr></w:pPr><w:r><w:rPr><w:rFonts w:ascii="Tahoma" w:hAnsi="Tahoma" w:cs="Tahoma"/></w:rPr><w:t>б)</w:t></w:r></w:p></w:tc></w:tr><w:tr w:rsidR="000C7A08" w14:paraId="6006C307" w14:textId="77777777" w:rsidTr="000C7A08"><w:tc><w:tcPr><w:tcW w:w="6204" w:type="dxa"/></w:tcPr><w:p w14:paraId="690E603A" w14:textId="77777777" w:rsidR="000C7A08" w:rsidRDefault="00B32969" w:rsidP="000C7A08"><w:pPr><w:spacing w:after="160" w:line="259" w:lineRule="auto"/><w:jc w:val="both"/><w:rPr><w:rFonts w:ascii="Tahoma" w:hAnsi="Tahoma" w:cs="Tahoma"/></w:rPr></w:pPr><w:r><w:rPr><w:noProof/></w:rPr><w:drawing><wp:inline distT="0" distB="0" distL="0" distR="0" wp14:anchorId="4E0EF164" wp14:editId="2E4F7779"><wp:extent cx="3932791" cy="2934000"/><wp:effectExtent l="0" t="0" r="10795" b="0"/><wp:docPr id="1" name="Диаграмма 1"><a:extLst xmlns:a="http://schemas.openxmlformats.org/drawingml/2006/main"><a:ext uri="{FF2B5EF4-FFF2-40B4-BE49-F238E27FC236}"><a16:creationId xmlns:a16="http://schemas.microsoft.com/office/drawing/2014/main" id="{8A7E628F-0223-4AF6-8BA2-629A38FC6549}"/></a:ext></a:extLst></wp:docPr><wp:cNvGraphicFramePr/><a:graphic xmlns:a="http://schemas.openxmlformats.org/drawingml/2006/main"><a:graphicData uri="http://schemas.openxmlformats.org/drawingml/2006/chart"><c:chart xmlns:c="http://schemas.openxmlformats.org/drawingml/2006/chart" xmlns:r="http://schemas.openxmlformats.org/officeDocument/2006/relationships" r:id="rId9"/></a:graphicData></a:graphic></wp:inline></w:drawing></w:r></w:p></w:tc><w:tc><w:tcPr><w:tcW w:w="3650" w:type="dxa"/></w:tcPr><w:p w14:paraId="678E7AB8" w14:textId="77777777" w:rsidR="000C7A08" w:rsidRDefault="00B32969" w:rsidP="000C7A08"><w:pPr><w:spacing w:after="160" w:line="259" w:lineRule="auto"/><w:jc w:val="both"/><w:rPr><w:rFonts w:ascii="Tahoma" w:hAnsi="Tahoma" w:cs="Tahoma"/></w:rPr></w:pPr><w:r><w:rPr><w:noProof/></w:rPr><w:drawing><wp:inline distT="0" distB="0" distL="0" distR="0" wp14:anchorId="39A7373F" wp14:editId="5EFF4101"><wp:extent cx="1954354" cy="2934000"/><wp:effectExtent l="0" t="0" r="8255" b="0"/><wp:docPr id="2" name="Диаграмма 2"><a:extLst xmlns:a="http://schemas.openxmlformats.org/drawingml/2006/main"><a:ext uri="{FF2B5EF4-FFF2-40B4-BE49-F238E27FC236}"><a16:creationId xmlns:a16="http://schemas.microsoft.com/office/drawing/2014/main" id="{7F9A85F1-E434-4149-AD0A-60FB199DC213}"/></a:ext></a:extLst></wp:docPr><wp:cNvGraphicFramePr/><a:graphic xmlns:a="http://schemas.openxmlformats.org/drawingml/2006/main"><a:graphicData uri="http://schemas.openxmlformats.org/drawingml/2006/chart"><c:chart xmlns:c="http://schemas.openxmlformats.org/drawingml/2006/chart" xmlns:r="http://schemas.openxmlformats.org/officeDocument/2006/relationships" r:id="rId10"/></a:graphicData></a:graphic></wp:inline></w:drawing></w:r></w:p></w:tc></w:tr></w:tbl><w:p w14:paraId="7E74C9BE" w14:textId="77777777" w:rsidR="000C7A08" w:rsidRDefault="000C7A08" w:rsidP="009D259D"><w:pPr><w:jc w:val="center"/><w:rPr><w:rFonts w:ascii="Tahoma" w:eastAsia="Calibri" w:hAnsi="Tahoma" w:cs="Tahoma"/><w:lang w:eastAsia="en-US"/></w:rPr></w:pPr><w:r><w:rPr><w:rFonts w:ascii="Tahoma" w:eastAsia="Calibri" w:hAnsi="Tahoma" w:cs="Tahoma"/><w:lang w:eastAsia="en-US"/></w:rPr><w:t>Рисунок 1 – Результаты измерений категории удароопасности</w:t></w:r></w:p><w:p w14:paraId="616C74EF" w14:textId="77777777" w:rsidR="002E44E6" w:rsidRPr="000C7A08" w:rsidRDefault="002E44E6" w:rsidP="002E44E6"><w:pPr><w:ind w:firstLine="709"/><w:jc w:val="both"/><w:rPr><w:rFonts w:ascii="Tahoma" w:eastAsia="Calibri" w:hAnsi="Tahoma" w:cs="Tahoma"/><w:lang w:eastAsia="en-US"/></w:rPr></w:pPr></w:p><w:p w14:paraId="18CED8DB" w14:textId="61BE95BC" w:rsidR="000C7A08" w:rsidRDefault="000C7A08" w:rsidP="002E44E6"><w:pPr><w:ind w:firstLine="709"/><w:jc w:val="both"/><w:rPr><w:rFonts w:ascii="Tahoma" w:hAnsi="Tahoma" w:cs="Tahoma"/><w:lang w:eastAsia="en-US"/></w:rPr></w:pPr><w:r w:rsidRPr="000C7A08"><w:rPr><w:rFonts w:ascii="Tahoma" w:eastAsia="Calibri" w:hAnsi="Tahoma" w:cs="Tahoma"/><w:lang w:eastAsia="en-US"/></w:rPr><w:t>Графическая область представлена диаграммой с пределами изменения</w:t></w:r><w:r w:rsidR="002E250D"><w:rPr><w:rFonts w:ascii="Tahoma" w:eastAsia="Calibri" w:hAnsi="Tahoma" w:cs="Tahoma"/><w:lang w:eastAsia="en-US"/></w:rPr><w:t xml:space="preserve"> отношений:</w:t></w:r><w:r w:rsidRPr="000C7A08"><w:rPr><w:rFonts w:ascii="Tahoma" w:eastAsia="Calibri" w:hAnsi="Tahoma" w:cs="Tahoma"/><w:lang w:eastAsia="en-US"/></w:rPr><w:t xml:space="preserve"> </w:t></w:r><m:oMath><m:f><m:fPr><m:type m:val="lin"/><m:ctrlPr><w:rPr><w:rFonts w:ascii="Cambria Math" w:eastAsia="Calibri" w:hAnsi="Cambria Math" w:cs="Tahoma"/><w:i/><w:lang w:eastAsia="en-US"/></w:rPr></m:ctrlPr></m:fPr><m:num><m:sSub><m:sSubPr><m:ctrlPr><w:rPr><w:rFonts w:ascii="Cambria Math" w:eastAsia="Calibri" w:hAnsi="Cambria Math" w:cs="Tahoma"/><w:i/><w:lang w:eastAsia="en-US"/></w:rPr></m:ctrlPr></m:sSubPr><m:e><m:r><w:rPr><w:rFonts w:ascii="Cambria Math" w:eastAsia="Calibri" w:hAnsi="Cambria Math" w:cs="Tahoma"/><w:lang w:eastAsia="en-US"/></w:rPr><m:t>X</m:t></m:r></m:e><m:sub><m:r><w:rPr><w:rFonts w:ascii="Cambria Math" w:eastAsia="Calibri" w:hAnsi="Cambria Math" w:cs="Tahoma"/><w:lang w:eastAsia="en-US"/></w:rPr><m:t>м</m:t></m:r></m:sub></m:sSub></m:num><m:den><m:r><w:rPr><w:rFonts w:ascii="Cambria Math" w:eastAsia="Calibri" w:hAnsi="Cambria Math" w:cs="Tahoma"/><w:lang w:eastAsia="en-US"/></w:rPr><m:t>h</m:t></m:r></m:den></m:f></m:oMath><w:r w:rsidR="00E532DF"><w:rPr><w:rFonts w:ascii="Tahoma" w:hAnsi="Tahoma" w:cs="Tahoma"/><w:lang w:eastAsia="en-US"/></w:rPr><w:t xml:space="preserve"> </w:t></w:r><w:r w:rsidR="002E250D"><w:rPr><w:rFonts w:ascii="Tahoma" w:hAnsi="Tahoma" w:cs="Tahoma"/><w:lang w:eastAsia="en-US"/></w:rPr><w:t xml:space="preserve">от 0 до </w:t></w:r><w:r w:rsidR="00F13654"><w:rPr><w:rFonts w:ascii="Tahoma" w:hAnsi="Tahoma" w:cs="Tahoma"/><w:lang w:eastAsia="en-US"/></w:rPr><w:t xml:space="preserve">1.25 </w:t></w:r><w:r w:rsidR="002E250D"><w:rPr><w:rFonts w:ascii="Tahoma" w:hAnsi="Tahoma" w:cs="Tahoma"/><w:lang w:eastAsia="en-US"/></w:rPr><w:t>(</w:t></w:r><w:r w:rsidR="00E532DF"><w:rPr><w:rFonts w:ascii="Tahoma" w:hAnsi="Tahoma" w:cs="Tahoma"/><w:lang w:eastAsia="en-US"/></w:rPr><w:t>ос</w:t></w:r><w:r w:rsidR="002E250D"><w:rPr><w:rFonts w:ascii="Tahoma" w:hAnsi="Tahoma" w:cs="Tahoma"/><w:lang w:eastAsia="en-US"/></w:rPr><w:t>ь</w:t></w:r><w:r w:rsidR="00E532DF"><w:rPr><w:rFonts w:ascii="Tahoma" w:hAnsi="Tahoma" w:cs="Tahoma"/><w:lang w:eastAsia="en-US"/></w:rPr><w:t xml:space="preserve"> абсцисс</w:t></w:r><w:r w:rsidR="002E250D"><w:rPr><w:rFonts w:ascii="Tahoma" w:hAnsi="Tahoma" w:cs="Tahoma"/><w:lang w:eastAsia="en-US"/></w:rPr><w:t>) и</w:t></w:r><w:r w:rsidRPr="000C7A08"><w:rPr><w:rFonts w:ascii="Tahoma" w:hAnsi="Tahoma" w:cs="Tahoma"/><w:lang w:eastAsia="en-US"/></w:rPr><w:t xml:space="preserve"> </w:t></w:r><m:oMath><m:f><m:fPr><m:type m:val="lin"/><m:ctrlPr><w:rPr><w:rFonts w:ascii="Cambria Math" w:eastAsia="Calibri" w:hAnsi="Cambria Math" w:cs="Tahoma"/><w:i/><w:lang w:eastAsia="en-US"/></w:rPr></m:ctrlPr></m:fPr><m:num><m:sSub><m:sSubPr><m:ctrlPr><w:rPr><w:rFonts w:ascii="Cambria Math" w:eastAsia="Calibri" w:hAnsi="Cambria Math" w:cs="Tahoma"/><w:i/><w:lang w:eastAsia="en-US"/></w:rPr></m:ctrlPr></m:sSubPr><m:e><m:r><w:rPr><w:rFonts w:ascii="Cambria Math" w:eastAsia="Calibri" w:hAnsi="Cambria Math" w:cs="Tahoma"/><w:lang w:val="en-US" w:eastAsia="en-US"/></w:rPr><m:t>N</m:t></m:r></m:e><m:sub><m:r><w:rPr><w:rFonts w:ascii="Cambria Math" w:eastAsia="Calibri" w:hAnsi="Cambria Math" w:cs="Tahoma"/><w:lang w:eastAsia="en-US"/></w:rPr><m:t>max</m:t></m:r></m:sub></m:sSub></m:num><m:den><m:sSub><m:sSubPr><m:ctrlPr><w:rPr><w:rFonts w:ascii="Cambria Math" w:eastAsia="Calibri" w:hAnsi="Cambria Math" w:cs="Tahoma"/><w:i/><w:lang w:eastAsia="en-US"/></w:rPr></m:ctrlPr></m:sSubPr><m:e><m:r><w:rPr><w:rFonts w:ascii="Cambria Math" w:eastAsia="Calibri" w:hAnsi="Cambria Math" w:cs="Tahoma"/><w:lang w:eastAsia="en-US"/></w:rPr><m:t>N</m:t></m:r></m:e><m:sub><m:r><w:rPr><w:rFonts w:ascii="Cambria Math" w:eastAsia="Calibri" w:hAnsi="Cambria Math" w:cs="Tahoma"/><w:lang w:eastAsia="en-US"/></w:rPr><m:t>0</m:t></m:r></m:sub></m:sSub></m:den></m:f></m:oMath><w:r w:rsidR="00891979"><w:rPr><w:rFonts w:ascii="Tahoma" w:hAnsi="Tahoma" w:cs="Tahoma"/><w:lang w:eastAsia="en-US"/></w:rPr><w:t xml:space="preserve"> </w:t></w:r><w:r w:rsidR="002E250D"><w:rPr><w:rFonts w:ascii="Tahoma" w:hAnsi="Tahoma" w:cs="Tahoma"/><w:lang w:eastAsia="en-US"/></w:rPr><w:t>от 0 до 40 (</w:t></w:r><w:r w:rsidR="00891979"><w:rPr><w:rFonts w:ascii="Tahoma" w:hAnsi="Tahoma" w:cs="Tahoma"/><w:lang w:eastAsia="en-US"/></w:rPr><w:t>ос</w:t></w:r><w:r w:rsidR="002E250D"><w:rPr><w:rFonts w:ascii="Tahoma" w:hAnsi="Tahoma" w:cs="Tahoma"/><w:lang w:eastAsia="en-US"/></w:rPr><w:t>ь</w:t></w:r><w:r w:rsidR="00891979"><w:rPr><w:rFonts w:ascii="Tahoma" w:hAnsi="Tahoma" w:cs="Tahoma"/><w:lang w:eastAsia="en-US"/></w:rPr><w:t xml:space="preserve"> ординат</w:t></w:r><w:r w:rsidR="002E250D"><w:rPr><w:rFonts w:ascii="Tahoma" w:hAnsi="Tahoma" w:cs="Tahoma"/><w:lang w:eastAsia="en-US"/></w:rPr><w:t>)</w:t></w:r><w:r w:rsidRPr="000C7A08"><w:rPr><w:rFonts w:ascii="Tahoma" w:hAnsi="Tahoma" w:cs="Tahoma"/><w:lang w:eastAsia="en-US"/></w:rPr><w:t>. Площадь диаграммы разделена линией на две зоны, соответствующие значен</w:t></w:r><w:r w:rsidR="00340017"><w:rPr><w:rFonts w:ascii="Tahoma" w:hAnsi="Tahoma" w:cs="Tahoma"/><w:lang w:eastAsia="en-US"/></w:rPr><w:t>иям параметров категории «ОПАСНО», «НЕОПАСНО</w:t></w:r><w:r w:rsidRPr="000C7A08"><w:rPr><w:rFonts w:ascii="Tahoma" w:hAnsi="Tahoma" w:cs="Tahoma"/><w:lang w:eastAsia="en-US"/></w:rPr><w:t>».</w:t></w:r></w:p><w:p w14:paraId="52620FD7" w14:textId="709DE9C7" w:rsidR="000C7A08" w:rsidRDefault="00340017" w:rsidP="002E44E6"><w:pPr><w:ind w:firstLine="709"/><w:jc w:val="both"/><w:rPr><w:rFonts w:ascii="Tahoma" w:hAnsi="Tahoma" w:cs="Tahoma"/><w:lang w:eastAsia="en-US"/></w:rPr></w:pPr><w:r><w:rPr><w:rFonts w:ascii="Tahoma" w:hAnsi="Tahoma" w:cs="Tahoma"/><w:lang w:eastAsia="en-US"/></w:rPr><w:t>По результатам измерений уст</w:t></w:r><w:r w:rsidR="000C7A08"><w:rPr><w:rFonts w:ascii="Tahoma" w:hAnsi="Tahoma" w:cs="Tahoma"/><w:lang w:eastAsia="en-US"/></w:rPr><w:t>ановлена категория ударо</w:t></w:r><w:r w:rsidR="009671A9"><w:rPr><w:rFonts w:ascii="Tahoma" w:hAnsi="Tahoma" w:cs="Tahoma"/><w:lang w:eastAsia="en-US"/></w:rPr><w:t>о</w:t></w:r><w:r w:rsidR="000C7A08"><w:rPr><w:rFonts w:ascii="Tahoma" w:hAnsi="Tahoma" w:cs="Tahoma"/><w:lang w:eastAsia="en-US"/></w:rPr><w:t xml:space="preserve">пасности </w:t></w:r><w:r w:rsidR="00B32969"><w:rPr><w:rFonts w:ascii="Tahoma" w:hAnsi="Tahoma" w:cs="Tahoma"/><w:lang w:eastAsia="en-US"/></w:rPr><w:t>НЕОПАСНО</w:t></w:r><w:r w:rsidR="00945422"><w:rPr><w:rFonts w:ascii="Tahoma" w:hAnsi="Tahoma" w:cs="Tahoma"/><w:lang w:eastAsia="en-US"/></w:rPr><w:t xml:space="preserve"> с коэффициентом запаса </w:t></w:r><w:r w:rsidR="00CD17DF" w:rsidRPr="00CD17DF"><w:rPr><w:rFonts w:ascii="Tahoma" w:hAnsi="Tahoma" w:cs="Tahoma"/></w:rPr><w:t>words</w:t></w:r><w:r w:rsidR="00945422"><w:rPr><w:rFonts w:ascii="Tahoma" w:hAnsi="Tahoma" w:cs="Tahoma"/><w:lang w:eastAsia="en-US"/></w:rPr><w:t>.</w:t></w:r></w:p><w:p w14:paraId="1706937C" w14:textId="77777777" w:rsidR="002E44E6" w:rsidRPr="000C7A08" w:rsidRDefault="002E44E6" w:rsidP="002E44E6"><w:pPr><w:ind w:firstLine="709"/><w:jc w:val="both"/><w:rPr><w:rFonts w:ascii="Tahoma" w:eastAsia="Calibri" w:hAnsi="Tahoma" w:cs="Tahoma"/><w:lang w:eastAsia="en-US"/></w:rPr></w:pPr></w:p><w:p w14:paraId="7254B07E" w14:textId="77777777" w:rsidR="0081783B" w:rsidRPr="00512446" w:rsidRDefault="000C7A08" w:rsidP="002911CA"><w:pPr><w:spacing w:after="40"/><w:rPr><w:rFonts w:ascii="Tahoma" w:hAnsi="Tahoma" w:cs="Tahoma"/><w:b/></w:rPr></w:pPr><w:r><w:rPr><w:rFonts w:ascii="Tahoma" w:hAnsi="Tahoma" w:cs="Tahoma"/><w:b/></w:rPr><w:t>В</w:t></w:r><w:r w:rsidR="003475CD" w:rsidRPr="00512446"><w:rPr><w:rFonts w:ascii="Tahoma" w:hAnsi="Tahoma" w:cs="Tahoma"/><w:b/></w:rPr><w:t>ыводы комиссии:</w:t></w:r></w:p><w:p w14:paraId="3603D7AC" w14:textId="77777777" w:rsidR="002911CA" w:rsidRPr="00512446" w:rsidRDefault="002911CA" w:rsidP="002911CA"><w:pPr><w:spacing w:after="40"/><w:rPr><w:rFonts w:ascii="Tahoma" w:hAnsi="Tahoma" w:cs="Tahoma"/><w:b/></w:rPr></w:pPr></w:p><w:p w14:paraId="4C75ABBD" w14:textId="60A65DB2" w:rsidR="003A458E" w:rsidRDefault="003A458E" w:rsidP="000A285B"><w:pPr><w:pStyle w:val="a8"/><w:numPr><w:ilvl w:val="0"/><w:numId w:val="44"/></w:numPr><w:tabs><w:tab w:val="left" w:pos="1134"/></w:tabs><w:jc w:val="both"/><w:rPr><w:rFonts w:ascii="Tahoma" w:hAnsi="Tahoma" w:cs="Tahoma"/></w:rPr></w:pPr><w:r><w:rPr><w:rFonts w:ascii="Tahoma" w:hAnsi="Tahoma" w:cs="Tahoma"/></w:rPr><w:t>В</w:t></w:r><w:r w:rsidR="00DD2356"><w:rPr><w:rFonts w:ascii="Tahoma" w:hAnsi="Tahoma" w:cs="Tahoma"/></w:rPr><w:t xml:space="preserve"> </w:t></w:r><w:r w:rsidR="009D259D"><w:rPr><w:rFonts w:ascii="Tahoma" w:hAnsi="Tahoma" w:cs="Tahoma"/></w:rPr><w:t>горной выработке</w:t></w:r><w:r w:rsidR="00CD17DF" w:rsidRPr="00CD17DF"><w:rPr><w:rFonts w:ascii="Tahoma" w:hAnsi="Tahoma" w:cs="Tahoma"/></w:rPr><w:t>words</w:t></w:r><w:r w:rsidR="00945422"><w:rPr><w:rFonts w:ascii="Tahoma" w:hAnsi="Tahoma" w:cs="Tahoma"/></w:rPr><w:t xml:space="preserve"> </w:t></w:r><w:r w:rsidR="00DD2356"><w:rPr><w:rFonts w:ascii="Tahoma" w:hAnsi="Tahoma" w:cs="Tahoma"/></w:rPr><w:t>на</w:t></w:r><w:r w:rsidR="00CD17DF" w:rsidRPr="00CD17DF"><w:rPr><w:rFonts w:ascii="Tahoma" w:hAnsi="Tahoma" w:cs="Tahoma"/></w:rPr><w:t>words</w:t></w:r><w:r><w:rPr><w:rFonts w:ascii="Tahoma" w:hAnsi="Tahoma" w:cs="Tahoma"/></w:rPr><w:t xml:space="preserve"> по результатам измерения установлена категория удароопасности</w:t></w:r><w:r w:rsidR="00DD2356"><w:rPr><w:rFonts w:ascii="Tahoma" w:hAnsi="Tahoma" w:cs="Tahoma"/></w:rPr><w:t xml:space="preserve"> </w:t></w:r><w:r w:rsidR="00CD17DF" w:rsidRPr="00CD17DF"><w:rPr><w:rFonts w:ascii="Tahoma" w:hAnsi="Tahoma" w:cs="Tahoma"/></w:rPr><w:t>words</w:t></w:r><w:r><w:rPr><w:rFonts w:ascii="Tahoma" w:hAnsi="Tahoma" w:cs="Tahoma"/></w:rPr><w:t xml:space="preserve">с </w:t></w:r><w:r><w:rPr><w:rFonts w:ascii="Tahoma" w:hAnsi="Tahoma" w:cs="Tahoma"/><w:lang w:eastAsia="en-US"/></w:rPr><w:t>коэффициентом запаса</w:t></w:r><w:r w:rsidR="000C58CA" w:rsidRPr="000C58CA"><w:rPr><w:rFonts w:ascii="Tahoma" w:hAnsi="Tahoma" w:cs="Tahoma"/><w:lang w:eastAsia="en-US"/></w:rPr><w:t xml:space="preserve"> </w:t></w:r><w:r w:rsidR="00CD17DF" w:rsidRPr="00CD17DF"><w:rPr><w:rFonts w:ascii="Tahoma" w:hAnsi="Tahoma" w:cs="Tahoma"/></w:rPr><w:t>words</w:t></w:r><w:r><w:rPr><w:rFonts w:ascii="Tahoma" w:hAnsi="Tahoma" w:cs="Tahoma"/><w:lang w:eastAsia="en-US"/></w:rPr><w:t xml:space="preserve">. </w:t></w:r></w:p><w:p w14:paraId="594A4BB9" w14:textId="0DB143BF" w:rsidR="00BA1FE7" w:rsidRPr="00512446" w:rsidRDefault="003A458E" w:rsidP="000A285B"><w:pPr><w:pStyle w:val="a8"/><w:numPr><w:ilvl w:val="0"/><w:numId w:val="44"/></w:numPr><w:tabs><w:tab w:val="left" w:pos="1134"/></w:tabs><w:jc w:val="both"/><w:rPr><w:rFonts w:ascii="Tahoma" w:hAnsi="Tahoma" w:cs="Tahoma"/></w:rPr></w:pPr><w:r><w:rPr><w:rFonts w:ascii="Tahoma" w:hAnsi="Tahoma" w:cs="Tahoma"/></w:rPr><w:t>Работы в</w:t></w:r><w:r w:rsidR="00BE2676" w:rsidRPr="00BE2676"><w:rPr><w:rFonts w:ascii="Tahoma" w:hAnsi="Tahoma" w:cs="Tahoma"/></w:rPr><w:t xml:space="preserve"> </w:t></w:r><w:r w:rsidR="00CD17DF" w:rsidRPr="00CD17DF"><w:rPr><w:rFonts w:ascii="Tahoma" w:hAnsi="Tahoma" w:cs="Tahoma"/></w:rPr><w:t>words</w:t></w:r><w:r><w:rPr><w:rFonts w:ascii="Tahoma" w:hAnsi="Tahoma" w:cs="Tahoma"/></w:rPr><w:t xml:space="preserve"> ведутся в соответствии с требованиями Указаний по безопасному ведению горных работ на Талнахском и Октябрьском месторождениях склонных и опасных по горным ударам</w:t></w:r><w:r w:rsidR="00BA1FE7" w:rsidRPr="00512446"><w:rPr><w:rFonts w:ascii="Tahoma" w:hAnsi="Tahoma" w:cs="Tahoma"/></w:rPr><w:t xml:space="preserve">. </w:t></w:r></w:p><w:p w14:paraId="1247DEC9" w14:textId="492E9AE2" w:rsidR="0092281B" w:rsidRDefault="0092281B" w:rsidP="0092281B"><w:pPr><w:ind w:firstLine="709"/><w:jc w:val="both"/><w:rPr><w:rFonts w:ascii="Tahoma" w:hAnsi="Tahoma" w:cs="Tahoma"/></w:rPr></w:pPr></w:p><w:p w14:paraId="1BF8A8F8" w14:textId="2D76F5E8" w:rsidR="002879B7" w:rsidRDefault="002879B7" w:rsidP="0092281B"><w:pPr><w:ind w:firstLine="709"/><w:jc w:val="both"/><w:rPr><w:rFonts w:ascii="Tahoma" w:hAnsi="Tahoma" w:cs="Tahoma"/></w:rPr></w:pPr></w:p><w:tbl><w:tblPr><w:tblStyle w:val="a7"/><w:tblW w:w="0" w:type="auto"/><w:tblBorders><w:top w:val="none" w:sz="0" w:space="0" w:color="auto"/><w:left w:val="none" w:sz="0" w:space="0" w:color="auto"/><w:bottom w:val="none" w:sz="0" w:space="0" w:color="auto"/><w:right w:val="none" w:sz="0" w:space="0" w:color="auto"/><w:insideH w:val="none" w:sz="0" w:space="0" w:color="auto"/><w:insideV w:val="none" w:sz="0" w:space="0" w:color="auto"/></w:tblBorders><w:tblLook w:val="04A0" w:firstRow="1" w:lastRow="0" w:firstColumn="1" w:lastColumn="0" w:noHBand="0" w:noVBand="1"/></w:tblPr><w:tblGrid><w:gridCol w:w="4530"/><w:gridCol w:w="4531"/></w:tblGrid><w:tr w:rsidR="002879B7" w14:paraId="341E4785" w14:textId="77777777" w:rsidTr="00A57BE3"><w:tc><w:tcPr><w:tcW w:w="4530" w:type="dxa"/></w:tcPr><w:p w14:paraId="2D012DA0" w14:textId="07B2CACD" w:rsidR="00A57BE3" w:rsidRPr="00A57BE3" w:rsidRDefault="002879B7" w:rsidP="0097182C"><w:pPr><w:spacing w:line="360" w:lineRule="auto"/><w:jc w:val="both"/><w:rPr><w:rFonts w:ascii="Tahoma" w:hAnsi="Tahoma" w:cs="Tahoma"/><w:b/></w:rPr></w:pPr><w:r w:rsidRPr="006531FA"><w:rPr><w:rFonts w:ascii="Tahoma" w:hAnsi="Tahoma" w:cs="Tahoma"/><w:b/></w:rPr><w:t>Председатель комиссии</w:t></w:r></w:p></w:tc><w:tc><w:tcPr><w:tcW w:w="4531" w:type="dxa"/></w:tcPr><w:p w14:paraId="21402027" w14:textId="687C6F39" w:rsidR="002879B7" w:rsidRPr="00CC10FE" w:rsidRDefault="00151A43" w:rsidP="002879B7"><w:pPr><w:jc w:val="right"/><w:rPr><w:rFonts w:ascii="Tahoma" w:hAnsi="Tahoma" w:cs="Tahoma"/><w:b/><w:bCs/><w:lang w:val="en-US"/></w:rPr></w:pPr><w:r w:rsidR="00CD17DF" w:rsidRPr="00CD17DF"><w:rPr><w:rFonts w:ascii="Tahoma" w:hAnsi="Tahoma" w:cs="Tahoma"/></w:rPr><w:t>words</w:t></w:r></w:p></w:tc></w:tr><w:tr w:rsidR="00A57BE3" w14:paraId="76D1BC9E" w14:textId="77777777" w:rsidTr="00A57BE3"><w:tc><w:tcPr><w:tcW w:w="4530" w:type="dxa"/></w:tcPr><w:p w14:paraId="20244F76" w14:textId="266BF9D6" w:rsidR="00B06420" w:rsidRPr="006531FA" w:rsidRDefault="00B06420" w:rsidP="00A57BE3"><w:pPr><w:jc w:val="both"/><w:rPr><w:rFonts w:ascii="Tahoma" w:hAnsi="Tahoma" w:cs="Tahoma"/><w:b/></w:rPr></w:pPr></w:p></w:tc><w:tc><w:tcPr><w:tcW w:w="4531" w:type="dxa"/></w:tcPr><w:p w14:paraId="2C092B60" w14:textId="77777777" w:rsidR="00A57BE3" w:rsidRDefault="00A57BE3" w:rsidP="002879B7"><w:pPr><w:jc w:val="right"/><w:rPr><w:rFonts w:ascii="Tahoma" w:hAnsi="Tahoma" w:cs="Tahoma"/><w:b/></w:rPr></w:pPr></w:p></w:tc></w:tr><w:tr w:rsidR="002879B7" w14:paraId="6CC08940" w14:textId="77777777" w:rsidTr="00A57BE3"><w:tc><w:tcPr><w:tcW w:w="4530" w:type="dxa"/></w:tcPr><w:p w14:paraId="08AA7A82" w14:textId="1316FF67" w:rsidR="002879B7" w:rsidRDefault="002879B7" w:rsidP="0092281B"><w:pPr><w:jc w:val="both"/><w:rPr><w:rFonts w:ascii="Tahoma" w:hAnsi="Tahoma" w:cs="Tahoma"/></w:rPr></w:pPr><w:r w:rsidRPr="006531FA"><w:rPr><w:rFonts w:ascii="Tahoma" w:hAnsi="Tahoma" w:cs="Tahoma"/><w:b/></w:rPr><w:t>Члены комиссии</w:t></w:r></w:p></w:tc><w:tc><w:tcPr><w:tcW w:w="4531" w:type="dxa"/></w:tcPr><w:p w14:paraId="0F2A81C1" w14:textId="2B27FF29" w:rsidR="002879B7" w:rsidRDefault="00CC10FE" w:rsidP="00A57BE3"><w:pPr><w:spacing w:line="360" w:lineRule="auto"/><w:jc w:val="right"/><w:rPr><w:rFonts w:ascii="Tahoma" w:hAnsi="Tahoma" w:cs="Tahoma"/></w:rPr></w:pPr><w:r w:rsidR="00CD17DF" w:rsidRPr="00CD17DF"><w:rPr><w:rFonts w:ascii="Tahoma" w:hAnsi="Tahoma" w:cs="Tahoma"/></w:rPr><w:t>words</w:t></w:r><w:proofErr w:type="gramEnd"/><w:r w:rsidR="002879B7"><w:rPr><w:rFonts w:ascii="Tahoma" w:hAnsi="Tahoma" w:cs="Tahoma"/><w:b/></w:rPr><w:t xml:space="preserve"> </w:t></w:r></w:p></w:tc></w:tr><w:tr w:rsidR="00CC10FE" w14:paraId="491E74B0" w14:textId="77777777" w:rsidTr="00A57BE3"><w:tc><w:tcPr><w:tcW w:w="4530" w:type="dxa"/></w:tcPr><w:p w14:paraId="315E48AC" w14:textId="77777777" w:rsidR="00CC10FE" w:rsidRDefault="00CC10FE" w:rsidP="00CC10FE"><w:pPr><w:jc w:val="both"/><w:rPr><w:rFonts w:ascii="Tahoma" w:hAnsi="Tahoma" w:cs="Tahoma"/></w:rPr></w:pPr></w:p></w:tc><w:tc><w:tcPr><w:tcW w:w="4531" w:type="dxa"/></w:tcPr><w:p w14:paraId="0916C208" w14:textId="6D791896" w:rsidR="00CC10FE" w:rsidRPr="00E250FE" w:rsidRDefault="00CC10FE" w:rsidP="00CC10FE"><w:pPr><w:spacing w:after="240" w:line="360" w:lineRule="auto"/><w:jc w:val="right"/><w:rPr><w:rFonts w:ascii="Tahoma" w:hAnsi="Tahoma" w:cs="Tahoma"/><w:b/></w:rPr></w:pPr><w:r w:rsidR="00CD17DF" w:rsidRPr="00CD17DF"><w:rPr><w:rFonts w:ascii="Tahoma" w:hAnsi="Tahoma" w:cs="Tahoma"/></w:rPr><w:t>words</w:t></w:r><w:proofErr w:type="gramEnd"/><w:r><w:rPr><w:rFonts w:ascii="Tahoma" w:hAnsi="Tahoma" w:cs="Tahoma"/><w:b/></w:rPr><w:t xml:space="preserve"> </w:t></w:r></w:p></w:tc></w:tr></w:tbl><w:p w14:paraId="47C48785" w14:textId="77777777" w:rsidR="002879B7" w:rsidRPr="00512446" w:rsidRDefault="002879B7" w:rsidP="0092281B"><w:pPr><w:ind w:firstLine="709"/><w:jc w:val="both"/><w:rPr><w:rFonts w:ascii="Tahoma" w:hAnsi="Tahoma" w:cs="Tahoma"/></w:rPr></w:pPr></w:p><w:p w14:paraId="6A3A920B" w14:textId="73FB7BBF" w:rsidR="007F55FB" w:rsidRDefault="007F55FB" w:rsidP="00D84344"><w:pPr><w:spacing w:after="160"/><w:rPr><w:rFonts w:ascii="Tahoma" w:eastAsia="Calibri" w:hAnsi="Tahoma" w:cs="Tahoma"/><w:b/><w:lang w:eastAsia="en-US"/></w:rPr></w:pPr><w:r w:rsidRPr="006531FA"><w:rPr><w:rFonts w:ascii="Tahoma" w:eastAsia="Calibri" w:hAnsi="Tahoma" w:cs="Tahoma"/><w:b/><w:lang w:eastAsia="en-US"/></w:rPr><w:tab/></w:r><w:r w:rsidRPr="006531FA"><w:rPr><w:rFonts w:ascii="Tahoma" w:eastAsia="Calibri" w:hAnsi="Tahoma" w:cs="Tahoma"/><w:b/><w:lang w:eastAsia="en-US"/></w:rPr><w:tab/><w:t xml:space="preserve">              </w:t></w:r><w:r w:rsidR="001F21A2"><w:rPr><w:rFonts w:ascii="Tahoma" w:eastAsia="Calibri" w:hAnsi="Tahoma" w:cs="Tahoma"/><w:b/><w:lang w:eastAsia="en-US"/></w:rPr><w:t xml:space="preserve">                            </w:t></w:r></w:p><w:p w14:paraId="6401A5B5" w14:textId="77777777" w:rsidR="00D84344" w:rsidRDefault="00D84344" w:rsidP="00D84344"><w:pPr><w:spacing w:after="160"/><w:rPr><w:rFonts w:ascii="Tahoma" w:eastAsia="Calibri" w:hAnsi="Tahoma" w:cs="Tahoma"/><w:b/><w:lang w:eastAsia="en-US"/></w:rPr></w:pPr></w:p><w:p w14:paraId="2E3EF84E" w14:textId="14046D62" w:rsidR="00FE37FD" w:rsidRPr="006531FA" w:rsidRDefault="007F55FB" w:rsidP="00D84344"><w:pPr><w:spacing w:after="160"/><w:rPr><w:rFonts w:ascii="Tahoma" w:eastAsia="Calibri" w:hAnsi="Tahoma" w:cs="Tahoma"/><w:b/><w:lang w:eastAsia="en-US"/></w:rPr></w:pPr><w:r w:rsidRPr="006531FA"><w:rPr><w:rFonts w:ascii="Tahoma" w:eastAsia="Calibri" w:hAnsi="Tahoma" w:cs="Tahoma"/><w:b/><w:lang w:eastAsia="en-US"/></w:rPr><w:tab/></w:r><w:r w:rsidRPr="006531FA"><w:rPr><w:rFonts w:ascii="Tahoma" w:eastAsia="Calibri" w:hAnsi="Tahoma" w:cs="Tahoma"/><w:b/><w:lang w:eastAsia="en-US"/></w:rPr><w:tab/><w:t xml:space="preserve">                          </w:t></w:r><w:r w:rsidR="003A458E"><w:rPr><w:rFonts w:ascii="Tahoma" w:eastAsia="Calibri" w:hAnsi="Tahoma" w:cs="Tahoma"/><w:b/><w:lang w:eastAsia="en-US"/></w:rPr><w:t xml:space="preserve">                              </w:t></w:r><w:r w:rsidR="002E250D"><w:rPr><w:rFonts w:ascii="Tahoma" w:eastAsia="Calibri" w:hAnsi="Tahoma" w:cs="Tahoma"/><w:b/><w:lang w:eastAsia="en-US"/></w:rPr><w:t xml:space="preserve">      </w:t></w:r></w:p><w:sectPr w:rsidR="00FE37FD" w:rsidRPr="006531FA" w:rsidSect="00A423B1"><w:footerReference w:type="default" r:id="rId11"/><w:pgSz w:w="11906" w:h="16838" w:code="9"/><w:pgMar w:top="1134" w:right="1134" w:bottom="1134" w:left="1701" w:header="567" w:footer="567" w:gutter="0"/><w:cols w:space="708"/><w:titlePg/><w:docGrid w:linePitch="360"/></w:sectPr></w:body></w:document>